GestureReceiverCode/arty-z7-gesture-receiver/arty-z7-gesture-receiver.srcs/sources_1/new/spi_master.v
`timescale 1ns / 1ps

 module spi_master(
    input wire clk,
    input wire reset,
    input wire start,
    input wire [7:0] data_tx,
    output reg [7:0] data_rx,
    output reg busy,
    output reg sck,
    output reg mosi, // Master Out Slave In: master send - slave get
    input wire miso // Master In Slave Out: master get - slave send
    );
    parameter CLK_DIV = 50;
    
    reg [5:0] clk_counter;
    reg [3:0] bit_counter;
    reg [7:0] tx_buffer;
    reg [7:0] rx_buffer;
    
    localparam IDLE = 0, TRANSFER = 1, DONE = 2;
    reg [1:0] state;
        
    always @(posedge clk) begin
        if (reset) begin
            state <= IDLE;
            busy <= 0;
            sck <= 0;
            mosi <= 0;
            bit_counter <= 0;
            clk_counter <= 0;
        end else begin
            case (state)
                IDLE: begin
                    busy <= 0;
                    sck <= 0;
                    if (start) begin
                        tx_buffer <= data_tx;
                        bit_counter <= 0;
                        clk_counter <= 0;
                        busy <= 1;
                        state <= TRANSFER;
                    end
                end
                
                TRANSFER: begin
                    if (clk_counter == CLK_DIV - 1) begin
                        clk_counter <= 0;
                        sck <= ~sck;
                        
                        if (sck == 0) begin
                            mosi <= tx_buffer[7 - bit_counter];
                        end else begin
                            rx_buffer[7 - bit_counter] <= miso;
                            bit_counter <= bit_counter + 1;
                            
                            if (bit_counter == 7) begin
                                state <= DONE;
                            end
                        end
                    end else begin
                        clk_counter <= clk_counter + 1;
                    end
                end
                
                DONE: begin
                    data_rx <= rx_buffer;
                    busy <= 0;
                    sck <= 0;
                    state <= IDLE;
                end
            endcase
        end
    end
endmodule

GestureReceiverCode/arty-z7-gesture-receiver/arty-z7-gesture-receiver.srcs/sim_1/new/tb_spi_master.v
`timescale 1ns / 1ps

// Testbench for the spi_master module, now supporting selective test execution.
module tb_spi_master;

    // ----------------------------------------------------
    // 1. PARAMETERS & CONSTANTS
    // ----------------------------------------------------
    parameter CLK_DIV = 50; 
    parameter CLK_PERIOD = 10; 
    
    // Test Data Patterns
    parameter DATA_TX_PATTERN_1 = 8'h5A; 
    parameter DATA_RX_EXPECTED_1 = 8'hC3; 
    parameter DATA_TX_PATTERN_2 = 8'hAA; 
    parameter DATA_RX_EXPECTED_2 = 8'h3C; 
    
    parameter TEST_CASE_ID = 3;
    
    // ----------------------------------------------------
    // 2. SIGNALS & DUT Instantiation
    // ----------------------------------------------------
    // DUT Inputs
    reg clk;
    reg reset;
    reg start;
    reg [7:0] data_tx;
    reg miso; // Master In Slave Out
    
    // DUT Outputs
    wire [7:0] data_rx;
    wire busy;
    wire sck;
    wire mosi; // Master Out Slave In
    
    // Internal variables for slave logic
    reg [7:0] slave_shift_reg;
    reg [3:0] slave_bit_index;
    
    
    // Device Under Test (DUT)
    spi_master #(.CLK_DIV(CLK_DIV)) DUT (
        .clk(clk),
        .reset(reset),
        .start(start),
        .data_tx(data_tx),
        .data_rx(data_rx),
        .busy(busy),
        .sck(sck),
        .mosi(mosi),
        .miso(miso)
    );
    
    
    // ----------------------------------------------------
    // 3. Clock Generation
    // ----------------------------------------------------
    always begin
        # (CLK_PERIOD / 2) clk = ~clk;
    end
    
    
    // ----------------------------------------------------
    // 4. COMMON TASK: Single SPI Transfer Transaction
    // ----------------------------------------------------
    // This task executes a single 8-bit SPI transaction (CPOL=0, CPHA=0).
    task run_transfer;
        input [7:0] tx_data_in;
        input [7:0] rx_data_expected_in;
        begin
            $display("\n=======================================================");
            $display("[%0t] STARTING TRANSFER: TX=%h, Expected RX=%h", $time, tx_data_in, rx_data_expected_in);
            $display("=======================================================");
            
            // 1. Setup Master and Slave
            data_tx = tx_data_in;
            slave_shift_reg = rx_data_expected_in;
            slave_bit_index = 0;
            start = 1;
            
            // CRUCIAL for CPHA=0: Set the first MISO bit (MSB) before the first SCK rising edge.
            miso <= rx_data_expected_in[7]; 
            
            @(posedge clk) #1;
            start = 0; 
            
            // Wait for BUSY to assert
            wait(busy == 1);
            $display("[%0t] Master is BUSY. Starting 8-bit loop.", $time);
            
            // 2. 8-Bit Transfer Loop 
            while (slave_bit_index < 8) begin
                
                // --- Step A: Wait for Posedge SCK (Master Samples MISO) ---
                @(posedge sck) begin
                    $display("[%0t] Posedge SCK (Bit %0d): MOSI (TX Master) = %b, MISO (RX Slave) = %b, Expected_RX_Bit = %b", 
                             $time, slave_bit_index, mosi, miso, slave_shift_reg[7 - slave_bit_index]);
                             
                    slave_bit_index <= slave_bit_index + 1; 
                end
                
                // --- Step B: Wait for Negedge SCK (Slave Sets MISO for next bit) ---
                @(negedge sck) begin
                    #1; 
                    
                    // Slave sets MISO for the NEXT bit (before the next posedge SCK)
                    if (slave_bit_index < 8) begin
                        miso <= slave_shift_reg[7 - slave_bit_index]; 
                    end
                end
            end
            
            // 3. Wait for Transaction End
            wait(busy == 0);
            $display("[%0t] Transfer Complete. Master is IDLE. SCK=%b.", $time, sck);
            
            // 4. Verification
            if (data_rx === slave_shift_reg) begin
                $display("--- VERIFICATION SUCCESS ---");
                $display("RX Data: %h (Matches Expected %h)", data_rx, slave_shift_reg);
            end else begin
                $error("--- VERIFICATION FAILED ---");
                $error("RX Data: %h (DOES NOT MATCH Expected %h)", data_rx, slave_shift_reg);
            end
        end
    endtask


    // ----------------------------------------------------
    // 5. MAIN TEST SCENARIOS (Selective Execution)
    // ----------------------------------------------------
    initial begin
        $display("----------------------------------------");
        $display("STARTING SELECTIVE SPI MASTER TESTBENCH");
        $display("Selected Test Case ID: %0d", TEST_CASE_ID);
        $display("----------------------------------------");
        
        // 1. Common Initialization and Reset
        clk = 0;
        reset = 1;
        start = 0;
        data_tx = 8'h00; 
        miso = 1'bZ; 
        
        # (CLK_PERIOD * 2) @(posedge clk);
        reset = 0; // Release Reset
        $display("[%0t] System Reset Released. Master is in IDLE state.", $time);
        
        
        // =======================================================================
        // EXECUTION CONTROL BLOCK
        // =======================================================================

        if (TEST_CASE_ID == 1) begin
            $display("Running Test Case 1: Standard Transfer (5A <-> C3)");
            run_transfer(DATA_TX_PATTERN_1, DATA_RX_EXPECTED_1);
        end 
        
        else if (TEST_CASE_ID == 2) begin
            $display("Running Test Case 2: Standard Transfer (AA <-> 3C)");
            run_transfer(DATA_TX_PATTERN_2, DATA_RX_EXPECTED_2);
        end
        
        else if (TEST_CASE_ID == 3) begin
            $display("Running Test Case 3: Reset During Transfer Test");
            
            // a. Start transfer
            data_tx = 8'h12;
            slave_shift_reg = 8'hFE;
            slave_bit_index = 0;
            start = 1;
            miso <= slave_shift_reg[7]; // Initial MISO set
            @(posedge clk) #1;
            start = 0;
            
            wait(busy == 1);
            $display("[%0t] Transfer started. Waiting for 3 bits to transfer...", $time);
            
            // b. Wait for first few SCK cycles (e.g., 3 bits)
            repeat (3) @(posedge sck);
            
            // c. Assert Reset
            $display("[%0t] *** ASSERTING HARD RESET DURING TRANSFER ***", $time);
            reset = 1;
            
            // d. Wait for a few clock cycles and check state
            # (CLK_PERIOD * 5) @(posedge clk);
            if (busy == 0 && sck == 0) begin
                $display("[%0t] RESET SUCCESSFUL: Busy=%b and SCK=%b are reset correctly.", $time, busy, sck);
            end else begin
                 $error("[%0t] RESET FAILED: Busy=%b or SCK=%b did not reset.", $time, busy, sck);
            end
            
            // e. Release Reset and confirm functionality is restored
            @(posedge clk) #1;
            reset = 0;
            $display("[%0t] Reset released. Running final check transfer (CD <-> AB).", $time);
            
            # (CLK_PERIOD * 10) @(posedge clk); 
            run_transfer(8'hCD, 8'hAB);
        end
        
        else begin
            $display("ERROR: Invalid TEST_CASE_ID (%0d). Please set TEST_CASE_ID to 1, 2, or 3.", TEST_CASE_ID);
        end
        
        // -----------------------------------------------------------------------
        
        // Finalize simulation
        $display("\n[%0t] Simulation finished.", $time);
        #100 $finish;
    end
    
    // VCD Dump for Waveform viewing
    initial begin
        $dumpfile("spi_master.vcd");
        $dumpvars(0, tb_spi_master);
    end

endmodule

GestureReceiverCode/arty-z7-gesture-receiver/arty-z7-gesture-receiver.sim/sim_1/behav/xsim/spi_master.vcd
$date
   Sun Nov 23 15:32:19 2025
$end
$version
  2018.2
$end
$timescale
  1ps
$end
$scope module tb_spi_master $end
$var reg 1 ! clk $end
$var reg 1 " reset $end
$var reg 1 # start $end
$var reg 8 $ data_tx [7:0] $end
$var reg 1 % miso $end
$var wire 8 & data_rx [7:0] $end
$var wire 1 ' busy $end
$var wire 1 ( sck $end
$var wire 1 ) mosi $end
$var reg 8 * slave_shift_reg [7:0] $end
$var reg 4 + slave_bit_index [3:0] $end
$var parameter 32 , CLK_DIV [31:0] $end
$var parameter 32 - CLK_PERIOD [31:0] $end
$var parameter 8 . DATA_TX_PATTERN_1 [7:0] $end
$var parameter 8 / DATA_RX_EXPECTED_1 [7:0] $end
$var parameter 8 0 DATA_TX_PATTERN_2 [7:0] $end
$var parameter 8 1 DATA_RX_EXPECTED_2 [7:0] $end
$var parameter 32 2 TEST_CASE_ID [31:0] $end
$scope module DUT $end
$var wire 1 3 clk $end
$var wire 1 4 reset $end
$var wire 1 5 start $end
$var wire 8 6 data_tx [7:0] $end
$var reg 8 7 data_rx [7:0] $end
$var reg 1 8 busy $end
$var reg 1 9 sck $end
$var reg 1 : mosi $end
$var wire 1 ; miso $end
$var reg 6 < clk_counter [5:0] $end
$var reg 4 = bit_counter [3:0] $end
$var reg 8 > tx_buffer [7:0] $end
$var reg 8 ? rx_buffer [7:0] $end
$var reg 2 @ state [1:0] $end
$var parameter 32 A CLK_DIV [31:0] $end
$var parameter 32 B IDLE [31:0] $end
$var parameter 32 C TRANSFER [31:0] $end
$var parameter 32 D DONE [31:0] $end
$upscope $end
$scope task run_transfer $end
$var reg 8 E tx_data_in [7:0] $end
$var reg 8 F rx_data_expected_in [7:0] $end
$upscope $end
$upscope $end
$enddefinitions $end
#0
$dumpvars
0!
1"
0#
b0 $
z%
bx &
x'
x(
x)
bx *
bx +
b110010 ,
b1010 -
b1011010 .
b11000011 /
b10101010 0
b111100 1
b11 2
03
14
05
b0 6
bx 7
x8
x9
x:
z;
bx <
bx =
bx >
bx ?
bx @
b110010 A
b0 B
b1 C
b10 D
bx E
bx F
$end
#5000
1!
0'
0(
0)
13
08
09
0:
b0 <
b0 =
b0 @
#10000
0!
03
#15000
1!
13
#20000
0!
03
#25000
1!
0"
1#
b10010 $
1%
1'
b11111110 *
b0 +
13
04
15
b10010 6
18
1;
b10010 >
b1 @
#30000
0!
03
#35000
1!
13
b1 <
#36000
0#
05
#40000
0!
03
#45000
1!
13
b10 <
#50000
0!
03
#55000
1!
13
b11 <
#60000
0!
03
#65000
1!
13
b100 <
#70000
0!
03
#75000
1!
13
b101 <
#80000
0!
03
#85000
1!
13
b110 <
#90000
0!
03
#95000
1!
13
b111 <
#100000
0!
03
#105000
1!
13
b1000 <
#110000
0!
03
#115000
1!
13
b1001 <
#120000
0!
03
#125000
1!
13
b1010 <
#130000
0!
03
#135000
1!
13
b1011 <
#140000
0!
03
#145000
1!
13
b1100 <
#150000
0!
03
#155000
1!
13
b1101 <
#160000
0!
03
#165000
1!
13
b1110 <
#170000
0!
03
#175000
1!
13
b1111 <
#180000
0!
03
#185000
1!
13
b10000 <
#190000
0!
03
#195000
1!
13
b10001 <
#200000
0!
03
#205000
1!
13
b10010 <
#210000
0!
03
#215000
1!
13
b10011 <
#220000
0!
03
#225000
1!
13
b10100 <
#230000
0!
03
#235000
1!
13
b10101 <
#240000
0!
03
#245000
1!
13
b10110 <
#250000
0!
03
#255000
1!
13
b10111 <
#260000
0!
03
#265000
1!
13
b11000 <
#270000
0!
03
#275000
1!
13
b11001 <
#280000
0!
03
#285000
1!
13
b11010 <
#290000
0!
03
#295000
1!
13
b11011 <
#300000
0!
03
#305000
1!
13
b11100 <
#310000
0!
03
#315000
1!
13
b11101 <
#320000
0!
03
#325000
1!
13
b11110 <
#330000
0!
03
#335000
1!
13
b11111 <
#340000
0!
03
#345000
1!
13
b100000 <
#350000
0!
03
#355000
1!
13
b100001 <
#360000
0!
03
#365000
1!
13
b100010 <
#370000
0!
03
#375000
1!
13
b100011 <
#380000
0!
03
#385000
1!
13
b100100 <
#390000
0!
03
#395000
1!
13
b100101 <
#400000
0!
03
#405000
1!
13
b100110 <
#410000
0!
03
#415000
1!
13
b100111 <
#420000
0!
03
#425000
1!
13
b101000 <
#430000
0!
03
#435000
1!
13
b101001 <
#440000
0!
03
#445000
1!
13
b101010 <
#450000
0!
03
#455000
1!
13
b101011 <
#460000
0!
03
#465000
1!
13
b101100 <
#470000
0!
03
#475000
1!
13
b101101 <
#480000
0!
03
#485000
1!
13
b101110 <
#490000
0!
03
#495000
1!
13
b101111 <
#500000
0!
03
#505000
1!
13
b110000 <
#510000
0!
03
#515000
1!
13
b110001 <
#520000
0!
03
#525000
1!
1(
13
19
b0 <
#530000
0!
03
#535000
1!
13
b1 <
#540000
0!
03
#545000
1!
13
b10 <
#550000
0!
03
#555000
1!
13
b11 <
#560000
0!
03
#565000
1!
13
b100 <
#570000
0!
03
#575000
1!
13
b101 <
#580000
0!
03
#585000
1!
13
b110 <
#590000
0!
03
#595000
1!
13
b111 <
#600000
0!
03
#605000
1!
13
b1000 <
#610000
0!
03
#615000
1!
13
b1001 <
#620000
0!
03
#625000
1!
13
b1010 <
#630000
0!
03
#635000
1!
13
b1011 <
#640000
0!
03
#645000
1!
13
b1100 <
#650000
0!
03
#655000
1!
13
b1101 <
#660000
0!
03
#665000
1!
13
b1110 <
#670000
0!
03
#675000
1!
13
b1111 <
#680000
0!
03
#685000
1!
13
b10000 <
#690000
0!
03
#695000
1!
13
b10001 <
#700000
0!
03
#705000
1!
13
b10010 <
#710000
0!
03
#715000
1!
13
b10011 <
#720000
0!
03
#725000
1!
13
b10100 <
#730000
0!
03
#735000
1!
13
b10101 <
#740000
0!
03
#745000
1!
13
b10110 <
#750000
0!
03
#755000
1!
13
b10111 <
#760000
0!
03
#765000
1!
13
b11000 <
#770000
0!
03
#775000
1!
13
b11001 <
#780000
0!
03
#785000
1!
13
b11010 <
#790000
0!
03
#795000
1!
13
b11011 <
#800000
0!
03
#805000
1!
13
b11100 <
#810000
0!
03
#815000
1!
13
b11101 <
#820000
0!
03
#825000
1!
13
b11110 <
#830000
0!
03
#835000
1!
13
b11111 <
#840000
0!
03
#845000
1!
13
b100000 <
#850000
0!
03
#855000
1!
13
b100001 <
#860000
0!
03
#865000
1!
13
b100010 <
#870000
0!
03
#875000
1!
13
b100011 <
#880000
0!
03
#885000
1!
13
b100100 <
#890000
0!
03
#895000
1!
13
b100101 <
#900000
0!
03
#905000
1!
13
b100110 <
#910000
0!
03
#915000
1!
13
b100111 <
#920000
0!
03
#925000
1!
13
b101000 <
#930000
0!
03
#935000
1!
13
b101001 <
#940000
0!
03
#945000
1!
13
b101010 <
#950000
0!
03
#955000
1!
13
b101011 <
#960000
0!
03
#965000
1!
13
b101100 <
#970000
0!
03
#975000
1!
13
b101101 <
#980000
0!
03
#985000
1!
13
b101110 <
#990000
0!
03
#995000
1!
13
b101111 <
#1000000
0!
03
#1005000
1!
13
b110000 <
#1010000
0!
03
#1015000
1!
13
b110001 <
#1020000
0!
03
#1025000
1!
0(
13
09
b0 <
b1 =
b1xxxxxxx ?
#1030000
0!
03
#1035000
1!
13
b1 <
#1040000
0!
03
#1045000
1!
13
b10 <
#1050000
0!
03
#1055000
1!
13
b11 <
#1060000
0!
03
#1065000
1!
13
b100 <
#1070000
0!
03
#1075000
1!
13
b101 <
#1080000
0!
03
#1085000
1!
13
b110 <
#1090000
0!
03
#1095000
1!
13
b111 <
#1100000
0!
03
#1105000
1!
13
b1000 <
#1110000
0!
03
#1115000
1!
13
b1001 <
#1120000
0!
03
#1125000
1!
13
b1010 <
#1130000
0!
03
#1135000
1!
13
b1011 <
#1140000
0!
03
#1145000
1!
13
b1100 <
#1150000
0!
03
#1155000
1!
13
b1101 <
#1160000
0!
03
#1165000
1!
13
b1110 <
#1170000
0!
03
#1175000
1!
13
b1111 <
#1180000
0!
03
#1185000
1!
13
b10000 <
#1190000
0!
03
#1195000
1!
13
b10001 <
#1200000
0!
03
#1205000
1!
13
b10010 <
#1210000
0!
03
#1215000
1!
13
b10011 <
#1220000
0!
03
#1225000
1!
13
b10100 <
#1230000
0!
03
#1235000
1!
13
b10101 <
#1240000
0!
03
#1245000
1!
13
b10110 <
#1250000
0!
03
#1255000
1!
13
b10111 <
#1260000
0!
03
#1265000
1!
13
b11000 <
#1270000
0!
03
#1275000
1!
13
b11001 <
#1280000
0!
03
#1285000
1!
13
b11010 <
#1290000
0!
03
#1295000
1!
13
b11011 <
#1300000
0!
03
#1305000
1!
13
b11100 <
#1310000
0!
03
#1315000
1!
13
b11101 <
#1320000
0!
03
#1325000
1!
13
b11110 <
#1330000
0!
03
#1335000
1!
13
b11111 <
#1340000
0!
03
#1345000
1!
13
b100000 <
#1350000
0!
03
#1355000
1!
13
b100001 <
#1360000
0!
03
#1365000
1!
13
b100010 <
#1370000
0!
03
#1375000
1!
13
b100011 <
#1380000
0!
03
#1385000
1!
13
b100100 <
#1390000
0!
03
#1395000
1!
13
b100101 <
#1400000
0!
03
#1405000
1!
13
b100110 <
#1410000
0!
03
#1415000
1!
13
b100111 <
#1420000
0!
03
#1425000
1!
13
b101000 <
#1430000
0!
03
#1435000
1!
13
b101001 <
#1440000
0!
03
#1445000
1!
13
b101010 <
#1450000
0!
03
#1455000
1!
13
b101011 <
#1460000
0!
03
#1465000
1!
13
b101100 <
#1470000
0!
03
#1475000
1!
13
b101101 <
#1480000
0!
03
#1485000
1!
13
b101110 <
#1490000
0!
03
#1495000
1!
13
b101111 <
#1500000
0!
03
#1505000
1!
13
b110000 <
#1510000
0!
03
#1515000
1!
13
b110001 <
#1520000
0!
03
#1525000
1!
1(
13
19
b0 <
#1530000
0!
03
#1535000
1!
13
b1 <
#1540000
0!
03
#1545000
1!
13
b10 <
#1550000
0!
03
#1555000
1!
13
b11 <
#1560000
0!
03
#1565000
1!
13
b100 <
#1570000
0!
03
#1575000
1!
13
b101 <
#1580000
0!
03
#1585000
1!
13
b110 <
#1590000
0!
03
#1595000
1!
13
b111 <
#1600000
0!
03
#1605000
1!
13
b1000 <
#1610000
0!
03
#1615000
1!
13
b1001 <
#1620000
0!
03
#1625000
1!
13
b1010 <
#1630000
0!
03
#1635000
1!
13
b1011 <
#1640000
0!
03
#1645000
1!
13
b1100 <
#1650000
0!
03
#1655000
1!
13
b1101 <
#1660000
0!
03
#1665000
1!
13
b1110 <
#1670000
0!
03
#1675000
1!
13
b1111 <
#1680000
0!
03
#1685000
1!
13
b10000 <
#1690000
0!
03
#1695000
1!
13
b10001 <
#1700000
0!
03
#1705000
1!
13
b10010 <
#1710000
0!
03
#1715000
1!
13
b10011 <
#1720000
0!
03
#1725000
1!
13
b10100 <
#1730000
0!
03
#1735000
1!
13
b10101 <
#1740000
0!
03
#1745000
1!
13
b10110 <
#1750000
0!
03
#1755000
1!
13
b10111 <
#1760000
0!
03
#1765000
1!
13
b11000 <
#1770000
0!
03
#1775000
1!
13
b11001 <
#1780000
0!
03
#1785000
1!
13
b11010 <
#1790000
0!
03
#1795000
1!
13
b11011 <
#1800000
0!
03
#1805000
1!
13
b11100 <
#1810000
0!
03
#1815000
1!
13
b11101 <
#1820000
0!
03
#1825000
1!
13
b11110 <
#1830000
0!
03
#1835000
1!
13
b11111 <
#1840000
0!
03
#1845000
1!
13
b100000 <
#1850000
0!
03
#1855000
1!
13
b100001 <
#1860000
0!
03
#1865000
1!
13
b100010 <
#1870000
0!
03
#1875000
1!
13
b100011 <
#1880000
0!
03
#1885000
1!
13
b100100 <
#1890000
0!
03
#1895000
1!
13
b100101 <
#1900000
0!
03
#1905000
1!
13
b100110 <
#1910000
0!
03
#1915000
1!
13
b100111 <
#1920000
0!
03
#1925000
1!
13
b101000 <
#1930000
0!
03
#1935000
1!
13
b101001 <
#1940000
0!
03
#1945000
1!
13
b101010 <
#1950000
0!
03
#1955000
1!
13
b101011 <
#1960000
0!
03
#1965000
1!
13
b101100 <
#1970000
0!
03
#1975000
1!
13
b101101 <
#1980000
0!
03
#1985000
1!
13
b101110 <
#1990000
0!
03
#1995000
1!
13
b101111 <
#2000000
0!
03
#2005000
1!
13
b110000 <
#2010000
0!
03
#2015000
1!
13
b110001 <
#2020000
0!
03
#2025000
1!
0(
13
09
b0 <
b10 =
b11xxxxxx ?
#2030000
0!
03
#2035000
1!
13
b1 <
#2040000
0!
03
#2045000
1!
13
b10 <
#2050000
0!
03
#2055000
1!
13
b11 <
#2060000
0!
03
#2065000
1!
13
b100 <
#2070000
0!
03
#2075000
1!
13
b101 <
#2080000
0!
03
#2085000
1!
13
b110 <
#2090000
0!
03
#2095000
1!
13
b111 <
#2100000
0!
03
#2105000
1!
13
b1000 <
#2110000
0!
03
#2115000
1!
13
b1001 <
#2120000
0!
03
#2125000
1!
13
b1010 <
#2130000
0!
03
#2135000
1!
13
b1011 <
#2140000
0!
03
#2145000
1!
13
b1100 <
#2150000
0!
03
#2155000
1!
13
b1101 <
#2160000
0!
03
#2165000
1!
13
b1110 <
#2170000
0!
03
#2175000
1!
13
b1111 <
#2180000
0!
03
#2185000
1!
13
b10000 <
#2190000
0!
03
#2195000
1!
13
b10001 <
#2200000
0!
03
#2205000
1!
13
b10010 <
#2210000
0!
03
#2215000
1!
13
b10011 <
#2220000
0!
03
#2225000
1!
13
b10100 <
#2230000
0!
03
#2235000
1!
13
b10101 <
#2240000
0!
03
#2245000
1!
13
b10110 <
#2250000
0!
03
#2255000
1!
13
b10111 <
#2260000
0!
03
#2265000
1!
13
b11000 <
#2270000
0!
03
#2275000
1!
13
b11001 <
#2280000
0!
03
#2285000
1!
13
b11010 <
#2290000
0!
03
#2295000
1!
13
b11011 <
#2300000
0!
03
#2305000
1!
13
b11100 <
#2310000
0!
03
#2315000
1!
13
b11101 <
#2320000
0!
03
#2325000
1!
13
b11110 <
#2330000
0!
03
#2335000
1!
13
b11111 <
#2340000
0!
03
#2345000
1!
13
b100000 <
#2350000
0!
03
#2355000
1!
13
b100001 <
#2360000
0!
03
#2365000
1!
13
b100010 <
#2370000
0!
03
#2375000
1!
13
b100011 <
#2380000
0!
03
#2385000
1!
13
b100100 <
#2390000
0!
03
#2395000
1!
13
b100101 <
#2400000
0!
03
#2405000
1!
13
b100110 <
#2410000
0!
03
#2415000
1!
13
b100111 <
#2420000
0!
03
#2425000
1!
13
b101000 <
#2430000
0!
03
#2435000
1!
13
b101001 <
#2440000
0!
03
#2445000
1!
13
b101010 <
#2450000
0!
03
#2455000
1!
13
b101011 <
#2460000
0!
03
#2465000
1!
13
b101100 <
#2470000
0!
03
#2475000
1!
13
b101101 <
#2480000
0!
03
#2485000
1!
13
b101110 <
#2490000
0!
03
#2495000
1!
13
b101111 <
#2500000
0!
03
#2505000
1!
13
b110000 <
#2510000
0!
03
#2515000
1!
13
b110001 <
#2520000
0!
03
#2525000
1!
1"
1(
13
14
19
b0 <
#2530000
0!
03
#2535000
1!
0'
0(
13
08
09
b0 =
b0 @
#2540000
0!
03
#2545000
1!
13
#2550000
0!
03
#2555000
1!
13
#2560000
0!
03
#2565000
1!
13
#2570000
0!
03
#2575000
1!
13
#2580000
0!
03
#2585000
1!
13
#2586000
0"
04
#2590000
0!
03
#2595000
1!
13
#2600000
0!
03
#2605000
1!
13
#2610000
0!
03
#2615000
1!
13
#2620000
0!
03
#2625000
1!
13
#2630000
0!
03
#2635000
1!
13
#2640000
0!
03
#2645000
1!
13
#2650000
0!
03
#2655000
1!
13
#2660000
0!
03
#2665000
1!
13
#2670000
0!
03
#2675000
1!
13
#2680000
0!
03
#2685000
1!
13
#2690000
0!
03
#2695000
1!
1#
b11001101 $
1%
1'
b10101011 *
13
15
b11001101 6
18
b11001101 >
b1 @
b11001101 E
b10101011 F
#2700000
0!
03
#2705000
1!
13
b1 <
#2706000
0#
05
#2710000
0!
03
#2715000
1!
13
b10 <
#2720000
0!
03
#2725000
1!
13
b11 <
#2730000
0!
03
#2735000
1!
13
b100 <
#2740000
0!
03
#2745000
1!
13
b101 <
#2750000
0!
03
#2755000
1!
13
b110 <
#2760000
0!
03
#2765000
1!
13
b111 <
#2770000
0!
03
#2775000
1!
13
b1000 <
#2780000
0!
03
#2785000
1!
13
b1001 <
#2790000
0!
03
#2795000
1!
13
b1010 <
#2800000
0!
03
#2805000
1!
13
b1011 <
#2810000
0!
03
#2815000
1!
13
b1100 <
#2820000
0!
03
#2825000
1!
13
b1101 <
#2830000
0!
03
#2835000
1!
13
b1110 <
#2840000
0!
03
#2845000
1!
13
b1111 <
#2850000
0!
03
#2855000
1!
13
b10000 <
#2860000
0!
03
#2865000
1!
13
b10001 <
#2870000
0!
03
#2875000
1!
13
b10010 <
#2880000
0!
03
#2885000
1!
13
b10011 <
#2890000
0!
03
#2895000
1!
13
b10100 <
#2900000
0!
03
#2905000
1!
13
b10101 <
#2910000
0!
03
#2915000
1!
13
b10110 <
#2920000
0!
03
#2925000
1!
13
b10111 <
#2930000
0!
03
#2935000
1!
13
b11000 <
#2940000
0!
03
#2945000
1!
13
b11001 <
#2950000
0!
03
#2955000
1!
13
b11010 <
#2960000
0!
03
#2965000
1!
13
b11011 <
#2970000
0!
03
#2975000
1!
13
b11100 <
#2980000
0!
03
#2985000
1!
13
b11101 <
#2990000
0!
03
#2995000
1!
13
b11110 <
#3000000
0!
03
#3005000
1!
13
b11111 <
#3010000
0!
03
#3015000
1!
13
b100000 <
#3020000
0!
03
#3025000
1!
13
b100001 <
#3030000
0!
03
#3035000
1!
13
b100010 <
#3040000
0!
03
#3045000
1!
13
b100011 <
#3050000
0!
03
#3055000
1!
13
b100100 <
#3060000
0!
03
#3065000
1!
13
b100101 <
#3070000
0!
03
#3075000
1!
13
b100110 <
#3080000
0!
03
#3085000
1!
13
b100111 <
#3090000
0!
03
#3095000
1!
13
b101000 <
#3100000
0!
03
#3105000
1!
13
b101001 <
#3110000
0!
03
#3115000
1!
13
b101010 <
#3120000
0!
03
#3125000
1!
13
b101011 <
#3130000
0!
03
#3135000
1!
13
b101100 <
#3140000
0!
03
#3145000
1!
13
b101101 <
#3150000
0!
03
#3155000
1!
13
b101110 <
#3160000
0!
03
#3165000
1!
13
b101111 <
#3170000
0!
03
#3175000
1!
13
b110000 <
#3180000
0!
03
#3185000
1!
13
b110001 <
#3190000
0!
03
#3195000
1!
1(
1)
b1 +
13
19
1:
b0 <
#3200000
0!
03
#3205000
1!
13
b1 <
#3210000
0!
03
#3215000
1!
13
b10 <
#3220000
0!
03
#3225000
1!
13
b11 <
#3230000
0!
03
#3235000
1!
13
b100 <
#3240000
0!
03
#3245000
1!
13
b101 <
#3250000
0!
03
#3255000
1!
13
b110 <
#3260000
0!
03
#3265000
1!
13
b111 <
#3270000
0!
03
#3275000
1!
13
b1000 <
#3280000
0!
03
#3285000
1!
13
b1001 <
#3290000
0!
03
#3295000
1!
13
b1010 <
#3300000
0!
03
#3305000
1!
13
b1011 <
#3310000
0!
03
#3315000
1!
13
b1100 <
#3320000
0!
03
#3325000
1!
13
b1101 <
#3330000
0!
03
#3335000
1!
13
b1110 <
#3340000
0!
03
#3345000
1!
13
b1111 <
#3350000
0!
03
#3355000
1!
13
b10000 <
#3360000
0!
03
#3365000
1!
13
b10001 <
#3370000
0!
03
#3375000
1!
13
b10010 <
#3380000
0!
03
#3385000
1!
13
b10011 <
#3390000
0!
03
#3395000
1!
13
b10100 <
#3400000
0!
03
#3405000
1!
13
b10101 <
#3410000
0!
03
#3415000
1!
13
b10110 <
#3420000
0!
03
#3425000
1!
13
b10111 <
#3430000
0!
03
#3435000
1!
13
b11000 <
#3440000
0!
03
#3445000
1!
13
b11001 <
#3450000
0!
03
#3455000
1!
13
b11010 <
#3460000
0!
03
#3465000
1!
13
b11011 <
#3470000
0!
03
#3475000
1!
13
b11100 <
#3480000
0!
03
#3485000
1!
13
b11101 <
#3490000
0!
03
#3495000
1!
13
b11110 <
#3500000
0!
03
#3505000
1!
13
b11111 <
#3510000
0!
03
#3515000
1!
13
b100000 <
#3520000
0!
03
#3525000
1!
13
b100001 <
#3530000
0!
03
#3535000
1!
13
b100010 <
#3540000
0!
03
#3545000
1!
13
b100011 <
#3550000
0!
03
#3555000
1!
13
b100100 <
#3560000
0!
03
#3565000
1!
13
b100101 <
#3570000
0!
03
#3575000
1!
13
b100110 <
#3580000
0!
03
#3585000
1!
13
b100111 <
#3590000
0!
03
#3595000
1!
13
b101000 <
#3600000
0!
03
#3605000
1!
13
b101001 <
#3610000
0!
03
#3615000
1!
13
b101010 <
#3620000
0!
03
#3625000
1!
13
b101011 <
#3630000
0!
03
#3635000
1!
13
b101100 <
#3640000
0!
03
#3645000
1!
13
b101101 <
#3650000
0!
03
#3655000
1!
13
b101110 <
#3660000
0!
03
#3665000
1!
13
b101111 <
#3670000
0!
03
#3675000
1!
13
b110000 <
#3680000
0!
03
#3685000
1!
13
b110001 <
#3690000
0!
03
#3695000
1!
0(
13
09
b0 <
b1 =
#3696000
0%
0;
#3700000
0!
03
#3705000
1!
13
b1 <
#3710000
0!
03
#3715000
1!
13
b10 <
#3720000
0!
03
#3725000
1!
13
b11 <
#3730000
0!
03
#3735000
1!
13
b100 <
#3740000
0!
03
#3745000
1!
13
b101 <
#3750000
0!
03
#3755000
1!
13
b110 <
#3760000
0!
03
#3765000
1!
13
b111 <
#3770000
0!
03
#3775000
1!
13
b1000 <
#3780000
0!
03
#3785000
1!
13
b1001 <
#3790000
0!
03
#3795000
1!
13
b1010 <
#3800000
0!
03
#3805000
1!
13
b1011 <
#3810000
0!
03
#3815000
1!
13
b1100 <
#3820000
0!
03
#3825000
1!
13
b1101 <
#3830000
0!
03
