GestureReceiverCode/arty-z7-gesture-receiver/arty-z7-gesture-receiver.srcs/sources_1/new/spi_master.v
`timescale 1ns / 1ps

 module spi_master(
    input wire clk,
    input wire reset,
    input wire start,
    input wire [7:0] data_tx,
    output reg [7:0] data_rx,
    output reg busy,
    output reg sck,
    output reg mosi, // Master Out Slave In: master send - slave get
    input wire miso // Master In Slave Out: master get - slave send
    );
    parameter CLK_DIV = 50;
    
    reg [5:0] clk_counter;
    reg [3:0] bit_counter;
    reg [7:0] tx_buffer;
    reg [7:0] rx_buffer;
    
    localparam IDLE = 0, TRANSFER = 1, DONE = 2;
    reg [1:0] state;
        
    always @(posedge clk) begin
        if (reset) begin
            state <= IDLE;
            busy <= 0;
            sck <= 0;
            mosi <= 0;
            bit_counter <= 0;
            clk_counter <= 0;
        end else begin
            case (state)
                IDLE: begin
                    busy <= 0;
                    sck <= 0;
                    if (start) begin
                        tx_buffer <= data_tx;
                        bit_counter <= 0;
                        clk_counter <= 0;
                        busy <= 1;
                        state <= TRANSFER;
                    end
                end
                
                TRANSFER: begin
                    if (clk_counter == CLK_DIV - 1) begin
                        clk_counter <= 0;
                        sck <= ~sck;
                        
                        if (sck == 0) begin
                            mosi <= tx_buffer[7 - bit_counter];
                        end else begin
                            rx_buffer[7 - bit_counter] <= miso;
                            bit_counter <= bit_counter + 1;
                            
                            if (bit_counter == 7) begin
                                state <= DONE;
                            end
                        end
                    end else begin
                        clk_counter <= clk_counter + 1;
                    end
                end
                
                DONE: begin
                    data_rx <= rx_buffer;
                    busy <= 0;
                    sck <= 0;
                    state <= IDLE;
                end
            endcase
        end
    end
endmodule

GestureReceiverCode/arty-z7-gesture-receiver/arty-z7-gesture-receiver.srcs/sim_1/new/tb_spi_master.v
`timescale 1ns / 1ps

module tb_spi_master;

    // ----------------------------------------------------
    // #1. Khai báo Tham s? và H?ng s? (PARAMETER & CONSTANTS)
    // ----------------------------------------------------
    // Tham s? CLK_DIV ph?i kh?p v?i module DUT
    parameter CLK_DIV = 50; 
    
    // T?c ?? ??ng h? (CLK_PERIOD)
    parameter CLK_PERIOD = 10; // 10ns -> 100MHz clock
    
    // ??nh ngh?a d? li?u mà SLAVE s? "g?i" (Master s? nh?n)
    parameter SLAVE_TX_DATA = 8'hC3; // 11000011
    
    
    // ----------------------------------------------------
    // #2. Khai báo Tín hi?u (SIGNALS)
    // ----------------------------------------------------
    reg clk;
    reg reset;
    reg start;
    reg [7:0] data_tx;
    reg miso; // Master In Slave Out (Slave g?i)
    
    wire [7:0] data_rx;
    wire busy;
    wire sck;
    wire mosi; // Master Out Slave In (Master g?i)
    
    // Bi?n ??m (ph?i ???c khai báo ? ph?m vi module)
    integer bit_count;

    
    // ----------------------------------------------------
    // #3. Kh?i t?o Module D??i Th? Nghi?m (DUT - Device Under Test)
    // ----------------------------------------------------
    spi_master #(.CLK_DIV(CLK_DIV)) DUT (
        .clk(clk),
        .reset(reset),
        .start(start),
        .data_tx(data_tx),
        .data_rx(data_rx),
        .busy(busy),
        .sck(sck),
        .mosi(mosi),
        .miso(miso)
    );
    
    
    // ----------------------------------------------------
    // #4. T?o Clock
    // ----------------------------------------------------
    always begin
        # (CLK_PERIOD / 2) clk = ~clk;
    end
    
    
    // ----------------------------------------------------
    // #5. K?ch b?n mô ph?ng chính (Test Scenario)
    // ----------------------------------------------------
    initial begin
        // 1. Kh?i t?o giá tr? ban ??u
        clk = 0;
        reset = 1;
        start = 0;
        data_tx = 8'hAA; 
        miso = 0;
        
        $display("----------------------------------------");
        $display("B?t ??u mô ph?ng SPI Master");
        
        // 2. Thi?t l?p l?i h? th?ng
        @(posedge clk) #1;
        reset = 0;
        $display("[%0t] Thi?t l?p l?i (Reset) hoàn t?t.", $time);
        
        // 3. Chu?n b? d? li?u và b?t ??u truy?n
        @(posedge clk) #1;
        data_tx = 8'h55; // D? li?u G?i: 01010101
        start = 1;
        $display("[%0t] Kích ho?t Start. D? li?u TX = %h", $time, data_tx);
        
        @(posedge clk) #1;
        start = 0; // T?t Start sau 1 chu k? clock
        
        // Kh?i t?o b? ??m bit t?i ?ây
        bit_count = 0;
        
        // 4. Mô ph?ng ph?n h?i t? Slave (miso)
        // L?p qua 8 bit
        while (bit_count < 8) begin
            
            // Ch? ??i SCK lên (Master ??c d? li?u t? Slave trên c?nh lên c?a SCK)
            @(posedge sck) begin
                // SCK lên: Master ??c MISO
                #1; // Th?i gian tr? nh? ?? Master k?p ??c
                
                // Cung c?p bit ti?p theo t? Slave (MSB tr??c)
                miso = SLAVE_TX_DATA[7 - bit_count]; 
                
                $display("[%0t] SCK Lên. Bit #%0d. MISO (Slave G?i) = %b. MOSI (Master G?i) = %b", 
                         $time, bit_count, miso, mosi);
                
                bit_count = bit_count + 1;
            end
            
            // Ch? ??i SCK xu?ng, ch? ?? ??m b?o chu trình ho?t ??ng
            @(negedge sck) begin
                // Master ??t MOSI cho bit ti?p theo t?i ?ây (d?a trên thi?t k? DUT)
            end
        end
        
        // 5. Ch? module chuy?n sang tr?ng thái DONE (busy=0)
        @(posedge busy) #1; 
        @(negedge busy) #1;
        
        // 6. Ki?m tra k?t qu?
        $display("----------------------------------------");
        $display("[%0t] Truy?n hoàn t?t. Busy = %b, SCK = %b.", $time, busy, sck);
        $display("D? li?u TX (G?i): %h", data_tx);
        $display("D? li?u RX (Nh?n): %h", data_rx);
        
        if (data_rx === SLAVE_TX_DATA) begin
            $display("--- KI?M TRA: THÀNH CÔNG! D? li?u nh?n kh?p v?i d? li?u Slave gi? l?p (%h).", SLAVE_TX_DATA);
        end else begin
            $display("--- KI?M TRA: TH?T B?I! D? li?u nh?n (%h) không kh?p v?i d? li?u Slave gi? l?p (%h).", data_rx, SLAVE_TX_DATA);
        end
        $display("----------------------------------------");
        
        // 7. K?t thúc mô ph?ng
        #100 $finish;
    end
    
    // Ghi các tín hi?u ra file VCD ?? xem d?ng sóng
    initial begin
        $dumpfile("spi_master.vcd");
        $dumpvars(0, tb_spi_master);
    end

endmodule

GestureReceiverCode/arty-z7-gesture-receiver/arty-z7-gesture-receiver.sim/sim_1/behav/xsim/spi_master.vcd
$date
   Sat Nov 22 21:59:52 2025
$end
$version
  2018.2
$end
$timescale
  1ps
$end
$scope module tb_spi_master $end
$var reg 1 ! clk $end
$var reg 1 " reset $end
$var reg 1 # start $end
$var reg 8 $ data_tx [7:0] $end
$var reg 1 % miso $end
$var wire 8 & data_rx [7:0] $end
$var wire 1 ' busy $end
$var wire 1 ( sck $end
$var wire 1 ) mosi $end
$var integer 32 * bit_count $end
$var parameter 32 + CLK_DIV [31:0] $end
$var parameter 32 , CLK_PERIOD [31:0] $end
$var parameter 8 - SLAVE_TX_DATA [7:0] $end
$scope module DUT $end
$var wire 1 . clk $end
$var wire 1 / reset $end
$var wire 1 0 start $end
$var wire 8 1 data_tx [7:0] $end
$var reg 8 2 data_rx [7:0] $end
$var reg 1 3 busy $end
$var reg 1 4 sck $end
$var reg 1 5 mosi $end
$var wire 1 6 miso $end
$var reg 6 7 clk_counter [5:0] $end
$var reg 4 8 bit_counter [3:0] $end
$var reg 8 9 tx_buffer [7:0] $end
$var reg 8 : rx_buffer [7:0] $end
$var reg 2 ; state [1:0] $end
$var parameter 32 < CLK_DIV [31:0] $end
$var parameter 32 = IDLE [31:0] $end
$var parameter 32 > TRANSFER [31:0] $end
$var parameter 32 ? DONE [31:0] $end
$upscope $end
$upscope $end
$enddefinitions $end
#0
$dumpvars
0!
1"
0#
b10101010 $
0%
bx &
x'
x(
x)
bx *
b110010 +
b1010 ,
b11000011 -
0.
1/
00
b10101010 1
bx 2
x3
x4
x5
06
bx 7
bx 8
bx 9
bx :
bx ;
b110010 <
b0 =
b1 >
b10 ?
$end
#5000
1!
0'
0(
0)
1.
03
04
05
b0 7
b0 8
b0 ;
#6000
0"
0/
#10000
0!
0.
#15000
1!
1.
#16000
1#
b1010101 $
10
b1010101 1
#20000
0!
0.
#25000
1!
1'
1.
13
b1010101 9
b1 ;
#26000
0#
b0 *
00
#30000
0!
0.
#35000
1!
1.
b1 7
#40000
0!
0.
#45000
1!
1.
b10 7
#50000
0!
0.
#55000
1!
1.
b11 7
#60000
0!
0.
#65000
1!
1.
b100 7
#70000
0!
0.
#75000
1!
1.
b101 7
#80000
0!
0.
#85000
1!
1.
b110 7
#90000
0!
0.
#95000
1!
1.
b111 7
#100000
0!
0.
#105000
1!
1.
b1000 7
#110000
0!
0.
#115000
1!
1.
b1001 7
#120000
0!
0.
#125000
1!
1.
b1010 7
#130000
0!
0.
#135000
1!
1.
b1011 7
#140000
0!
0.
#145000
1!
1.
b1100 7
#150000
0!
0.
#155000
1!
1.
b1101 7
#160000
0!
0.
#165000
1!
1.
b1110 7
#170000
0!
0.
#175000
1!
1.
b1111 7
#180000
0!
0.
#185000
1!
1.
b10000 7
#190000
0!
0.
#195000
1!
1.
b10001 7
#200000
0!
0.
#205000
1!
1.
b10010 7
#210000
0!
0.
#215000
1!
1.
b10011 7
#220000
0!
0.
#225000
1!
1.
b10100 7
#230000
0!
0.
#235000
1!
1.
b10101 7
#240000
0!
0.
#245000
1!
1.
b10110 7
#250000
0!
0.
#255000
1!
1.
b10111 7
#260000
0!
0.
#265000
1!
1.
b11000 7
#270000
0!
0.
#275000
1!
1.
b11001 7
#280000
0!
0.
#285000
1!
1.
b11010 7
#290000
0!
0.
#295000
1!
1.
b11011 7
#300000
0!
0.
#305000
1!
1.
b11100 7
#310000
0!
0.
#315000
1!
1.
b11101 7
#320000
0!
0.
#325000
1!
1.
b11110 7
#330000
0!
0.
#335000
1!
1.
b11111 7
#340000
0!
0.
#345000
1!
1.
b100000 7
#350000
0!
0.
#355000
1!
1.
b100001 7
#360000
0!
0.
#365000
1!
1.
b100010 7
#370000
0!
0.
#375000
1!
1.
b100011 7
#380000
0!
0.
#385000
1!
1.
b100100 7
#390000
0!
0.
#395000
1!
1.
b100101 7
#400000
0!
0.
#405000
1!
1.
b100110 7
#410000
0!
0.
#415000
1!
1.
b100111 7
#420000
0!
0.
#425000
1!
1.
b101000 7
#430000
0!
0.
#435000
1!
1.
b101001 7
#440000
0!
0.
#445000
1!
1.
b101010 7
#450000
0!
0.
#455000
1!
1.
b101011 7
#460000
0!
0.
#465000
1!
1.
b101100 7
#470000
0!
0.
#475000
1!
1.
b101101 7
#480000
0!
0.
#485000
1!
1.
b101110 7
#490000
0!
0.
#495000
1!
1.
b101111 7
#500000
0!
0.
#505000
1!
1.
b110000 7
#510000
0!
0.
#515000
1!
1.
b110001 7
#520000
0!
0.
#525000
1!
1(
1.
14
b0 7
#526000
1%
b1 *
16
#530000
0!
0.
#535000
1!
1.
b1 7
#540000
0!
0.
#545000
1!
1.
b10 7
#550000
0!
0.
#555000
1!
1.
b11 7
#560000
0!
0.
#565000
1!
1.
b100 7
#570000
0!
0.
#575000
1!
1.
b101 7
#580000
0!
0.
#585000
1!
1.
b110 7
#590000
0!
0.
#595000
1!
1.
b111 7
#600000
0!
0.
#605000
1!
1.
b1000 7
#610000
0!
0.
#615000
1!
1.
b1001 7
#620000
0!
0.
#625000
1!
1.
b1010 7
#630000
0!
0.
#635000
1!
1.
b1011 7
#640000
0!
0.
#645000
1!
1.
b1100 7
#650000
0!
0.
#655000
1!
1.
b1101 7
#660000
0!
0.
#665000
1!
1.
b1110 7
#670000
0!
0.
#675000
1!
1.
b1111 7
#680000
0!
0.
#685000
1!
1.
b10000 7
#690000
0!
0.
#695000
1!
1.
b10001 7
#700000
0!
0.
#705000
1!
1.
b10010 7
#710000
0!
0.
#715000
1!
1.
b10011 7
#720000
0!
0.
#725000
1!
1.
b10100 7
#730000
0!
0.
#735000
1!
1.
b10101 7
#740000
0!
0.
#745000
1!
1.
b10110 7
#750000
0!
0.
#755000
1!
1.
b10111 7
#760000
0!
0.
#765000
1!
1.
b11000 7
#770000
0!
0.
#775000
1!
1.
b11001 7
#780000
0!
0.
#785000
1!
1.
b11010 7
#790000
0!
0.
#795000
1!
1.
b11011 7
#800000
0!
0.
#805000
1!
1.
b11100 7
#810000
0!
0.
#815000
1!
1.
b11101 7
#820000
0!
0.
#825000
1!
1.
b11110 7
#830000
0!
0.
#835000
1!
1.
b11111 7
#840000
0!
0.
#845000
1!
1.
b100000 7
#850000
0!
0.
#855000
1!
1.
b100001 7
#860000
0!
0.
#865000
1!
1.
b100010 7
#870000
0!
0.
#875000
1!
1.
b100011 7
#880000
0!
0.
#885000
1!
1.
b100100 7
#890000
0!
0.
#895000
1!
1.
b100101 7
#900000
0!
0.
#905000
1!
1.
b100110 7
#910000
0!
0.
#915000
1!
1.
b100111 7
#920000
0!
0.
#925000
1!
1.
b101000 7
#930000
0!
0.
#935000
1!
1.
b101001 7
#940000
0!
0.
#945000
1!
1.
b101010 7
#950000
0!
0.
#955000
1!
1.
b101011 7
#960000
0!
0.
#965000
1!
1.
b101100 7
#970000
0!
0.
#975000
1!
1.
b101101 7
#980000
0!
0.
#985000
1!
1.
b101110 7
#990000
0!
0.
#995000
1!
1.
b101111 7
