GestureReceiverCode/arty-z7-gesture-receiver/arty-z7-gesture-receiver.srcs/sources_1/new/spi_master.v
module spi_master (
    // Clock và Reset
    input clk,
    input rst_n,
    
    // Tham s? chia t?n s? SCK
    input [7:0] spi_clk_div, 
    
    // COntroller
    input start_transfer,
    output reg transfer_done,
    
    // Output
    input [7:0] data_in,
    output reg [7:0] data_out,

    // Giao di?n SPI
    output reg spi_sck, // reg vì ???c ?i?u khi?n trong always
    output reg spi_mosi, // reg vì ???c ?i?u khi?n trong always
    input spi_miso
);

    // ??nh ngh?a các h?ng s? tr?ng thái (thay vì enum)
    `define IDLE     2'b00
    `define TRANSMIT 2'b01
    `define DONE     2'b10
    
    // Các thanh ghi tr?ng thái (reg)
    reg [1:0] current_state, next_state;
    
    // B? ??m xung ??ng h? SPI (reg)
    reg [7:0] sck_counter;
    
    // Tín hi?u ?ánh d?u s? ki?n SCK (reg)
    reg sck_tick; 
    
    // B? ??m bit (reg)
    reg [3:0] bit_counter;
    
    // Thanh ghi t?m th?i cho d? li?u (reg)
    reg [7:0] shift_reg_tx, shift_reg_rx;

    // ----------------------------------------------------
    // 1. Logic Chuy?n tr?ng thái t? h?p (next_state logic)
    // ----------------------------------------------------
    always @(current_state or start_transfer or bit_counter) begin
        next_state = current_state; // M?c ??nh gi? nguyên tr?ng thái
        case (current_state)
            `IDLE: begin
                if (start_transfer) // Get cmd from controller
                    next_state = `TRANSMIT;
            end
    
            `TRANSMIT: begin
                if (bit_counter == 8) // Done transmit 1 byte (8 bits) 
                    next_state = `DONE;
            end
    
            `DONE: begin
                next_state = `IDLE;
            end
            default: next_state = `IDLE;
        endcase
    end
    
    // ----------------------------------------------------
    // 2. Logic Tu?n t? (Xung clock, D?ch chuy?n, ??ng ký tr?ng thái)
    // ----------------------------------------------------
    always @(posedge clk or negedge rst_n) begin
        if (!rst_n) begin
            // Reset
            current_state <= `IDLE;
            transfer_done <= 1'b0;
            bit_counter <= 4'h0;
            shift_reg_tx <= 8'h00;
            shift_reg_rx <= 8'h00;
            data_out <= 8'h00;
            
            sck_counter <= 8'h00;
            spi_sck <= 1'b0;
            sck_tick <= 1'b0;
            spi_mosi <= 1'b0;
        end else begin
            // C?p nh?t tr?ng thái
            current_state <= next_state;
            transfer_done <= 1'b0; // M?c ??nh là th?p
    
            // Logic Xung SCK và Tick
            if (current_state == `TRANSMIT) begin
                if (sck_counter == spi_clk_div - 1) begin
                    sck_counter <= 8'h00;
                    spi_sck <= ~spi_sck; 
                    sck_tick <= 1'b1;
                end else begin
                    sck_counter <= sck_counter + 1;
                    sck_tick <= 1'b0;
                end
            end else begin
                // ??m b?o SCK ? m?c th?p khi IDLE/DONE
                spi_sck <= 1'b0; 
                sck_counter <= 8'h00;
                sck_tick <= 1'b0;
            end
    
            // Logic FSM
            case (current_state)
                `IDLE: begin
                    if (start_transfer) begin
                        shift_reg_tx <= data_in; // Download data_in
                        bit_counter <= 4'h0;
                    end
                    spi_mosi <= 1'b0; // MOSI th?p khi IDLE
                end
    
                `TRANSMIT: begin
                    // T?o MOSI: G?i bit MSB tr??c
                    spi_mosi <= shift_reg_tx[7];
                    
    
                    // D?ch chuy?n trên c?nh LÊN c?a SCK (CPOL=0, CPHA=0)
                    if (sck_tick & spi_sck) begin // Ki?m tra (sck_tick=1) và (spi_sck=1)
                        shift_reg_tx <= shift_reg_tx << 1; 
                        shift_reg_rx <= {shift_reg_rx[6:0], spi_miso}; 
                        bit_counter <= bit_counter + 1;
                    end
                    
                end
    
                `DONE: begin
                    data_out <= shift_reg_rx;
                    transfer_done <= 1'b1;
                    spi_mosi <= 1'b0;
                    $display("[SPI] Done. Data_out %h", data_out);
                end
            endcase
        end
    end
endmodule

GestureReceiverCode/arty-z7-gesture-receiver/arty-z7-gesture-receiver.srcs/sim_1/new/tb_spi_master.v
`timescale 1ns / 1ps

module spi_master_tb;

    // ----------------------------------------------------
    // 1. Khai báo tín hi?u Testbench
    // ----------------------------------------------------
    reg clk;
    reg rst_n;
    
    reg [7:0] spi_clk_div = 8'd8; 
    
    reg start_transfer;
    reg [7:0] data_in;
    reg spi_miso;

    wire transfer_done;
    wire [7:0] data_out;
    wire spi_sck;
    wire spi_mosi;
    
    parameter TEST_DATA_TX = 8'b10101111; // d? li?u master g?i
    parameter TEST_DATA_RX = 8'b01010000; // d? li?u slave tr? v?
    
    reg [7:0] expected_data_out;
    integer i;

    // ----------------------------------------------------
    // 2. Kh?i t?o DUT
    // ----------------------------------------------------
    spi_master DUT (
        .clk(clk),
        .rst_n(rst_n),
        .spi_clk_div(spi_clk_div),
        
        .start_transfer(start_transfer),
        .transfer_done(transfer_done),
        .data_in(data_in),
        .data_out(data_out),

        .spi_sck(spi_sck),
        .spi_mosi(spi_mosi),
        .spi_miso(spi_miso)
    );

    // ----------------------------------------------------
    // 3. T?o Clock 100 MHz
    // ----------------------------------------------------
    always #5 clk = ~clk; 

    // ----------------------------------------------------
    // 4. K?ch b?n Test
    // ----------------------------------------------------
    initial begin
        $display("--- Begin Testbench spi_master ---");
        clk = 1'b0;
        rst_n = 1'b0;
        start_transfer = 1'b0;
        data_in = 8'h00;
        spi_miso = 1'b1;
        
        // Reset
        #100; 
        rst_n = 1'b1;
        $display("Reset.");

        // Thi?t l?p d? li?u
        data_in = TEST_DATA_TX;
        expected_data_out = TEST_DATA_RX;
        
        // B?t ??u truy?n
        #10 start_transfer = 1'b1;
        #10 start_transfer = 1'b0; 
        
        $display("Transfer TX=%b", data_in);

        // Mô ph?ng 8 bit truy?n/nh?n
        for (i = 0; i < 8; i = i + 1) begin
            @(posedge spi_sck) begin
                // Slave ??a d? li?u ra MISO
                spi_miso <= expected_data_out[7 - i];

                // Ki?m tra MOSI có ?úng không
                if (spi_mosi !== TEST_DATA_TX[7 - i]) begin
                    $display("-> LOI MOSI: Bit %0d, MOSI=%b, mong ??i=%b", 
                              i, spi_mosi, TEST_DATA_TX[7 - i]);
                end else begin
                    $display("-> DUNG MOSI: Bit %0d, MOSI=%b", i, spi_mosi);
                end

                // In thông tin RX
                $display("@%0t: Bit %0d TX=%b, RX(MISO)=%b", 
                          $time, i, spi_mosi, spi_miso);
            end
        end
        
        // Ch? k?t thúc truy?n
        @(posedge transfer_done);
        $display("--- K?t thúc truy?n. Th?i gian: %0t ---", $time);

        // Ki?m tra d? li?u nh?n
        if (data_out == expected_data_out) begin
            $display("-> THANH CONG RX: data_out=%b kh?p v?i mong ??i=%b", 
                      data_out, expected_data_out);
        end else begin
            $display("-> THAT BAI RX: data_out=%b, mong ??i=%b", 
                      data_out, expected_data_out);
        end
        
        #100 $finish; 
    end
    
    // ----------------------------------------------------
    // 5. Ghi sóng (Tùy ch?n)
    // ----------------------------------------------------
    initial begin
        $dumpfile("spi_master.vcd");
        $dumpvars(0, spi_master_tb);
    end

endmodule

GestureReceiverCode/arty-z7-gesture-receiver/arty-z7-gesture-receiver.sim/sim_1/behav/xsim/spi_master.vcd
$date
   Tue Nov 25 08:14:14 2025
$end
$version
  2018.2
$end
$timescale
  1ps
$end
$scope module spi_master_tb $end
$var reg 1 ! clk $end
$var reg 1 " rst_n $end
$var reg 8 # spi_clk_div [7:0] $end
$var reg 1 $ start_transfer $end
$var reg 8 % data_in [7:0] $end
$var reg 1 & spi_miso $end
$var wire 1 ' transfer_done $end
$var wire 8 ( data_out [7:0] $end
$var wire 1 ) spi_sck $end
$var wire 1 * spi_mosi $end
$var reg 8 + expected_data_out [7:0] $end
$var integer 32 , i $end
$var parameter 8 - TEST_DATA_TX [7:0] $end
$var parameter 8 . TEST_DATA_RX [7:0] $end
$scope module DUT $end
$var wire 1 / clk $end
$var wire 1 0 rst_n $end
$var wire 8 1 spi_clk_div [7:0] $end
$var wire 1 2 start_transfer $end
$var reg 1 3 transfer_done $end
$var wire 8 4 data_in [7:0] $end
$var reg 8 5 data_out [7:0] $end
$var reg 1 6 spi_sck $end
$var reg 1 7 spi_mosi $end
$var wire 1 8 spi_miso $end
$var reg 2 9 current_state [1:0] $end
$var reg 2 : next_state [1:0] $end
$var reg 8 ; sck_counter [7:0] $end
$var reg 1 < sck_tick $end
$var reg 4 = bit_counter [3:0] $end
$var reg 8 > shift_reg_tx [7:0] $end
$var reg 8 ? shift_reg_rx [7:0] $end
$upscope $end
$upscope $end
$enddefinitions $end
#0
$dumpvars
0!
0"
b1000 #
0$
b0 %
1&
0'
b0 (
0)
0*
bx +
bx ,
b10101111 -
b1010000 .
0/
00
b1000 1
02
03
b0 4
b0 5
06
07
18
b0 9
b0 :
b0 ;
0<
b0 =
b0 >
b0 ?
$end
#5000
1!
1/
#10000
0!
0/
#15000
1!
1/
#20000
0!
0/
#25000
1!
1/
#30000
0!
0/
#35000
1!
1/
#40000
0!
0/
#45000
1!
1/
#50000
0!
0/
#55000
1!
1/
#60000
0!
0/
#65000
1!
1/
#70000
0!
0/
#75000
1!
1/
#80000
0!
0/
#85000
1!
1/
#90000
0!
0/
#95000
1!
1/
#100000
0!
1"
b10101111 %
b1010000 +
0/
10
b10101111 4
#105000
1!
1/
#110000
0!
1$
0/
12
b1 :
#115000
1!
1/
b1 9
b10101111 >
#120000
0!
0$
b0 ,
0/
02
#125000
1!
1*
1/
17
b1 ;
#130000
0!
0/
#135000
1!
1/
b10 ;
#140000
0!
0/
#145000
1!
1/
b11 ;
#150000
0!
0/
#155000
1!
1/
b100 ;
#160000
0!
0/
#165000
1!
1/
b101 ;
#170000
0!
0/
#175000
1!
1/
b110 ;
#180000
0!
0/
#185000
1!
1/
b111 ;
#190000
0!
0/
#195000
1!
0&
1)
b1 ,
1/
16
08
b0 ;
1<
#200000
0!
0/
#205000
1!
1/
b1 ;
0<
b1 =
b1011110 >
#210000
0!
0/
#215000
1!
0*
1/
07
b10 ;
#220000
0!
0/
#225000
1!
1/
b11 ;
#230000
0!
0/
#235000
1!
1/
b100 ;
#240000
0!
0/
#245000
1!
1/
b101 ;
#250000
0!
0/
#255000
1!
1/
b110 ;
#260000
0!
0/
#265000
1!
1/
b111 ;
#270000
0!
0/
#275000
1!
0)
1/
06
b0 ;
1<
#280000
0!
0/
#285000
1!
1/
b1 ;
0<
#290000
0!
0/
#295000
1!
1/
b10 ;
#300000
0!
0/
#305000
1!
1/
b11 ;
#310000
0!
0/
#315000
1!
1/
b100 ;
#320000
0!
0/
#325000
1!
1/
b101 ;
#330000
0!
0/
#335000
1!
1/
b110 ;
#340000
0!
0/
#345000
1!
1/
b111 ;
#350000
0!
0/
#355000
1!
1&
1)
b10 ,
1/
16
18
b0 ;
1<
#360000
0!
0/
#365000
1!
1/
b1 ;
0<
b10 =
b10111100 >
b1 ?
#370000
0!
0/
#375000
1!
1*
1/
17
b10 ;
#380000
0!
0/
#385000
1!
1/
b11 ;
#390000
0!
0/
#395000
1!
1/
b100 ;
#400000
0!
0/
#405000
1!
1/
b101 ;
#410000
0!
0/
#415000
1!
1/
b110 ;
#420000
0!
0/
#425000
1!
1/
b111 ;
#430000
0!
0/
#435000
1!
0)
1/
06
b0 ;
1<
#440000
0!
0/
#445000
1!
1/
b1 ;
0<
#450000
0!
0/
#455000
1!
1/
b10 ;
#460000
0!
0/
#465000
1!
1/
b11 ;
#470000
0!
0/
#475000
1!
1/
b100 ;
#480000
0!
0/
#485000
1!
1/
b101 ;
#490000
0!
0/
#495000
1!
1/
b110 ;
#500000
0!
0/
#505000
1!
1/
b111 ;
#510000
0!
0/
#515000
1!
0&
1)
b11 ,
1/
16
08
b0 ;
1<
#520000
0!
0/
#525000
1!
1/
b1 ;
0<
b11 =
b1111000 >
b10 ?
#530000
0!
0/
#535000
1!
0*
1/
07
b10 ;
#540000
0!
0/
#545000
1!
1/
b11 ;
#550000
0!
0/
#555000
1!
1/
b100 ;
#560000
0!
0/
#565000
1!
1/
b101 ;
#570000
0!
0/
#575000
1!
1/
b110 ;
#580000
0!
0/
#585000
1!
1/
b111 ;
#590000
0!
0/
#595000
1!
0)
1/
06
b0 ;
1<
#600000
0!
0/
#605000
1!
1/
b1 ;
0<
#610000
0!
0/
#615000
1!
1/
b10 ;
#620000
0!
0/
#625000
1!
1/
b11 ;
#630000
0!
0/
#635000
1!
1/
b100 ;
#640000
0!
0/
#645000
1!
1/
b101 ;
#650000
0!
0/
#655000
1!
1/
b110 ;
#660000
0!
0/
#665000
1!
1/
b111 ;
#670000
0!
0/
#675000
1!
1&
1)
b100 ,
1/
16
18
b0 ;
1<
#680000
0!
0/
#685000
1!
1/
b1 ;
0<
b100 =
b11110000 >
b101 ?
#690000
0!
0/
#695000
1!
1*
1/
17
b10 ;
#700000
0!
0/
#705000
1!
1/
b11 ;
#710000
0!
0/
#715000
1!
1/
b100 ;
#720000
0!
0/
#725000
1!
1/
b101 ;
#730000
0!
0/
#735000
1!
1/
b110 ;
#740000
0!
0/
#745000
1!
1/
b111 ;
#750000
0!
0/
#755000
1!
0)
1/
06
b0 ;
1<
#760000
0!
0/
#765000
1!
1/
b1 ;
0<
#770000
0!
0/
#775000
1!
1/
b10 ;
#780000
0!
0/
#785000
1!
1/
b11 ;
#790000
0!
0/
#795000
1!
1/
b100 ;
#800000
0!
0/
#805000
1!
1/
b101 ;
#810000
0!
0/
#815000
1!
1/
b110 ;
#820000
0!
0/
#825000
1!
1/
b111 ;
#830000
0!
0/
#835000
1!
0&
1)
b101 ,
1/
16
08
b0 ;
1<
#840000
0!
0/
#845000
1!
1/
b1 ;
0<
b101 =
b11100000 >
b1010 ?
#850000
0!
0/
#855000
1!
1/
b10 ;
#860000
0!
0/
#865000
1!
1/
b11 ;
#870000
0!
0/
#875000
1!
1/
b100 ;
#880000
0!
0/
#885000
1!
1/
b101 ;
#890000
0!
0/
#895000
1!
1/
b110 ;
#900000
0!
0/
#905000
1!
1/
b111 ;
#910000
0!
0/
#915000
1!
0)
1/
06
b0 ;
1<
#920000
0!
0/
#925000
1!
1/
b1 ;
0<
#930000
0!
0/
#935000
1!
1/
b10 ;
#940000
0!
0/
#945000
1!
1/
b11 ;
#950000
0!
0/
#955000
1!
1/
b100 ;
#960000
0!
0/
#965000
1!
1/
b101 ;
#970000
0!
0/
#975000
1!
1/
b110 ;
#980000
0!
0/
#985000
1!
1/
b111 ;
#990000
0!
0/
#995000
1!
0&
1)
b110 ,
1/
16
b0 ;
1<
#1000000
0!
0/
#1005000
1!
1/
b1 ;
0<
b110 =
b11000000 >
b10100 ?
#1010000
0!
0/
#1015000
1!
1/
b10 ;
#1020000
0!
0/
#1025000
1!
1/
b11 ;
#1030000
0!
0/
#1035000
1!
1/
b100 ;
#1040000
0!
0/
#1045000
1!
1/
b101 ;
#1050000
0!
0/
#1055000
1!
1/
b110 ;
#1060000
0!
0/
#1065000
1!
1/
b111 ;
#1070000
0!
0/
#1075000
1!
0)
1/
06
b0 ;
1<
#1080000
0!
0/
#1085000
1!
1/
b1 ;
0<
#1090000
0!
0/
#1095000
1!
1/
b10 ;
#1100000
0!
0/
#1105000
1!
1/
b11 ;
#1110000
0!
0/
#1115000
1!
1/
b100 ;
#1120000
0!
0/
#1125000
1!
1/
b101 ;
#1130000
0!
0/
#1135000
1!
1/
b110 ;
#1140000
0!
0/
#1145000
1!
1/
b111 ;
#1150000
0!
0/
#1155000
1!
0&
1)
b111 ,
1/
16
b0 ;
1<
#1160000
0!
0/
#1165000
1!
1/
b1 ;
0<
b111 =
b10000000 >
b101000 ?
#1170000
0!
0/
#1175000
1!
1/
b10 ;
#1180000
0!
0/
#1185000
1!
1/
b11 ;
#1190000
0!
0/
#1195000
1!
1/
b100 ;
#1200000
0!
0/
#1205000
1!
1/
b101 ;
#1210000
0!
0/
#1215000
1!
1/
b110 ;
#1220000
0!
0/
#1225000
1!
1/
b111 ;
#1230000
0!
0/
#1235000
1!
0)
1/
06
b0 ;
1<
#1240000
0!
0/
#1245000
1!
1/
b1 ;
0<
#1250000
0!
0/
#1255000
1!
1/
b10 ;
#1260000
0!
0/
#1265000
1!
1/
b11 ;
#1270000
0!
0/
#1275000
1!
1/
b100 ;
#1280000
0!
0/
#1285000
1!
1/
b101 ;
#1290000
0!
0/
#1295000
1!
1/
b110 ;
#1300000
0!
0/
#1305000
1!
1/
b111 ;
#1310000
0!
0/
#1315000
1!
0&
1)
b1000 ,
1/
16
b0 ;
1<
#1320000
0!
0/
#1325000
1!
1/
b10 :
b1 ;
0<
b1000 =
b0 >
b1010000 ?
#1330000
0!
0/
#1335000
1!
0*
1/
07
b10 9
b0 :
b10 ;
#1340000
0!
0/
#1345000
1!
1'
b1010000 (
0)
1/
13
b1010000 5
06
b0 9
b0 ;
#1350000
0!
0/
#1355000
1!
0'
1/
03
