GestureReceiverCode/arty-z7-gesture-receiver/arty-z7-gesture-receiver.srcs/sources_1/new/spi_master.v
module spi_master (
    // Clock and Reset
    input clk,
    input rst_n,
    
    // SCK frequency divider parameter
    input [7:0] spi_clk_div,
    
    // Controller interface
    input start_transfer,
    output reg transfer_done,
    
    // Data interface
    input [7:0] data_in,
    output reg [7:0] data_out,

    // SPI interface
    output reg spi_sck, // reg because controlled in always block
    output reg spi_mosi, // reg because controlled in always block
    input spi_miso
);

    // State definition
    `define IDLE     2'b00
    `define TRANSMIT 2'b01
    `define DONE     2'b10
    
    // State registers
    reg [1:0] current_state, next_state;
    
    // SPI clock counter
    reg [7:0] sck_counter;
    
    // SCK tick signal
    reg sck_tick; 
    
    // Bit counter
    reg [3:0] bit_counter;
    
    // Temporary data registers
    reg [7:0] shift_reg_tx, shift_reg_rx;

    // ----------------------------------------------------
    // 1. Combinational Next State Logic
    // ----------------------------------------------------
    always @(current_state or start_transfer or bit_counter) begin
        next_state = current_state; // Default: maintain current state
        case (current_state)
            `IDLE: begin
                if (start_transfer) // Get cmd from controller
                    next_state = `TRANSMIT;
            end
    
            `TRANSMIT: begin
                if (bit_counter == 8) // Done transmit 1 byte (8 bits) 
                    next_state = `DONE;
            end
    
            `DONE: begin
                next_state = `IDLE;
            end
            default: next_state = `IDLE;
        endcase
    end
    
    // ----------------------------------------------------
    // 2. Sequential Logic (Clock, Shift registers, State registers)
    // ----------------------------------------------------
    always @(posedge clk or negedge rst_n) begin
        if (!rst_n) begin
            // Reset all registers
            current_state <= `IDLE;
            transfer_done <= 1'b0;
            bit_counter <= 4'h0;
            shift_reg_tx <= 8'h00;
            shift_reg_rx <= 8'h00;
            data_out <= 8'h00;
            
            sck_counter <= 8'h00;
            spi_sck <= 1'b0;
            sck_tick <= 1'b0;
            spi_mosi <= 1'b0;
        end else begin
            // Update state
            current_state <= next_state;
            transfer_done <= 1'b0; // Default is low
    
            // SCK generation and tick logic
            if (current_state == `TRANSMIT) begin
                if (sck_counter == spi_clk_div - 1) begin
                    sck_counter <= 8'h00;
                    spi_sck <= ~spi_sck; 
                    sck_tick <= 1'b1;
                end else begin
                    sck_counter <= sck_counter + 1;
                    sck_tick <= 1'b0;
                end
            end else begin
                // Ensure SCK is low when IDLE/DONE
                spi_sck <= 1'b0; 
                sck_counter <= 8'h00;
                sck_tick <= 1'b0;
            end
    
            // FSM logic
            case (current_state)
                `IDLE: begin
                    if (start_transfer) begin
                        shift_reg_tx <= data_in; // Load input data
                        bit_counter <= 4'h0;
                    end
                    spi_mosi <= 1'b0; // MOSI low when IDLE
                end
    
                `TRANSMIT: begin
                    // Generate MOSI: Send MSB first
                    spi_mosi <= shift_reg_tx[7];
                    
    
                    // Shift on rising edge of SCK (CPOL=0, CPHA=0)
                    if (sck_tick & spi_sck) begin // Check (sck_tick=1) and (spi_sck=1)
                        shift_reg_tx <= shift_reg_tx << 1; 
                        shift_reg_rx <= {shift_reg_rx[6:0], spi_miso}; 
                        bit_counter <= bit_counter + 1;
                    end
                    
                end
    
                `DONE: begin
                    data_out <= shift_reg_rx;
                    transfer_done <= 1'b1;
                    spi_mosi <= 1'b0;
                    $display("[SPI] Done. Data_out %h", data_out);
                end
            endcase
        end
    end
endmodule

GestureReceiverCode/arty-z7-gesture-receiver/arty-z7-gesture-receiver.srcs/sim_1/imports/new/tb_spi_master_new.v
`timescale 1ns / 1ps

module tb_spi_master;

    // ----------------------------------------------------
    // 1. Testbench Signal Declarations
    // ----------------------------------------------------
    reg clk;
    reg rst_n;
    
    reg [7:0] spi_clk_div; 
    
    reg start_transfer;
    reg [7:0] data_in;
    reg spi_miso;

    wire transfer_done;
    wire [7:0] data_out;
    wire spi_sck;
    wire spi_mosi;
    
    // Test parameters
    parameter CLK_PERIOD = 10; // 100MHz clock
    parameter TEST_DATA_TX = 8'hA5; // Test data to transmit (10100101)
    parameter TEST_DATA_RX = 8'h5A; // Test data to receive (01011010)
    
    // Internal variables
    reg [7:0] expected_rx_data;
    reg [7:0] miso_shift_reg;
    integer bit_count;
    integer test_count;
    integer error_count;

    // ----------------------------------------------------
    // 2. DUT Instantiation
    // ----------------------------------------------------
    spi_master DUT (
        .clk(clk),
        .rst_n(rst_n),
        .spi_clk_div(spi_clk_div),
        
        .start_transfer(start_transfer),
        .transfer_done(transfer_done),
        .data_in(data_in),
        .data_out(data_out),

        .spi_sck(spi_sck),
        .spi_mosi(spi_mosi),
        .spi_miso(spi_miso)
    );

    // ----------------------------------------------------
    // 3. Clock Generation (100 MHz)
    // ----------------------------------------------------
    initial clk = 0;
    always #(CLK_PERIOD/2) clk = ~clk;

    // ----------------------------------------------------
    // 4. Test Scenarios
    // ----------------------------------------------------
    initial begin
        $display("=== SPI Master Testbench Started ===");
        
        // Initialize signals
        rst_n = 0;
        start_transfer = 0;
        data_in = 0;
        spi_miso = 0;
        spi_clk_div = 8'd4; // Divide by 4 for faster simulation
        test_count = 0;
        error_count = 0;
        
        // Reset sequence
        repeat(5) @(posedge clk);
        rst_n = 1;
        repeat(2) @(posedge clk);
        $display("[%0t] Reset completed", $time);

        // Test 1: Basic SPI transfer
        test_spi_transfer(TEST_DATA_TX, TEST_DATA_RX);
        
        // Test 2: All zeros
        test_spi_transfer(8'h00, 8'hFF);
        
        // Test 3: All ones
        test_spi_transfer(8'hFF, 8'h00);
        
        // Test 4: Alternating pattern
        test_spi_transfer(8'hAA, 8'h55);
        
        // Test 5: Different clock divider
        spi_clk_div = 8'd8;
        test_spi_transfer(8'h3C, 8'hC3);
        
        // Test summary
        $display("\n=== Test Summary ===");
        $display("Total tests: %0d", test_count);
        $display("Errors: %0d", error_count);
        if (error_count == 0) begin
            $display("*** ALL TESTS PASSED ***");
        end else begin
            $display("*** %0d TESTS FAILED ***", error_count);
        end
        
        #100;
        $finish;
    end
    
    // ----------------------------------------------------
    // 5. Task: Test SPI Transfer
    // ----------------------------------------------------
    task test_spi_transfer;
        input [7:0] tx_data;
        input [7:0] rx_data;
        begin
            test_count = test_count + 1;
            $display("\n--- Test %0d: TX=0x%h, Expected RX=0x%h ---", test_count, tx_data, rx_data);
            
            // Setup test data
            data_in = tx_data;
            expected_rx_data = rx_data;
            miso_shift_reg = rx_data;
            bit_count = 0;
            
            // Start transfer
            @(posedge clk);
            start_transfer = 1;
            @(posedge clk);
            start_transfer = 0;
            
            $display("[%0t] Transfer started", $time);
            
            // Wait for transfer completion
            @(posedge transfer_done);
            
            // Verify results
            if (data_out == expected_rx_data) begin
                $display("[%0t] ✓ PASS: RX data correct (0x%h)", $time, data_out);
            end else begin
                $display("[%0t] ✗ FAIL: RX data incorrect (got 0x%h, expected 0x%h)", 
                         $time, data_out, expected_rx_data);
                error_count = error_count + 1;
            end
            
            repeat(5) @(posedge clk); // Wait between tests
        end
    endtask
    
    // ----------------------------------------------------
    // 6. MISO Simulation (Slave Response)
    // ----------------------------------------------------
    always @(posedge spi_sck or negedge rst_n) begin
        if (!rst_n) begin
            bit_count <= 0;
        end else begin
            // Send MSB first on MISO
            spi_miso <= miso_shift_reg[7-bit_count];
            $display("[%0t] SCK rising: Bit %0d, MOSI=%b, MISO=%b", 
                     $time, bit_count, spi_mosi, miso_shift_reg[7-bit_count]);
            bit_count <= bit_count + 1;
        end
    end
    
    // Reset bit counter when not transmitting
    always @(negedge spi_sck or negedge rst_n) begin
        if (!rst_n) begin
            // Reset handled above
        end else begin
            // Optional: Add additional logic on falling edge if needed
        end
    end
    
    // Reset bit counter when transfer starts
    always @(posedge start_transfer) begin
        bit_count <= 0;
    end
    
    // ----------------------------------------------------
    // 7. Monitors and Assertions
    // ----------------------------------------------------
    
    // Monitor SCK frequency
    real sck_period;
    time last_sck_time = 0;
    
    always @(posedge spi_sck) begin
        if (last_sck_time != 0) begin
            sck_period = $time - last_sck_time;
        end
        last_sck_time = $time;
    end
    
    // Monitor transfer duration
    time transfer_start_time;
    time transfer_end_time;
    
    always @(posedge start_transfer) begin
        transfer_start_time = $time;
    end
    
    always @(posedge transfer_done) begin
        transfer_end_time = $time;
        $display("[%0t] Transfer completed in %0t ns", $time, transfer_end_time - transfer_start_time);
    end
    
    // ----------------------------------------------------
    // 8. Waveform Dump
    // ----------------------------------------------------
    initial begin
        $dumpfile("tb_spi_master.vcd");
        $dumpvars(0, tb_spi_master);
    end

endmodule

GestureReceiverCode/arty-z7-gesture-receiver/arty-z7-gesture-receiver.sim/sim_1/behav/xsim/tb_spi_master.vcd
$date
   Wed Nov 26 15:24:05 2025
$end
$version
  2018.2
$end
$timescale
  1ps
$end
$scope module tb_spi_master $end
$var reg 1 ! clk $end
$var reg 1 " rst_n $end
$var reg 8 # spi_clk_div [7:0] $end
$var reg 1 $ start_transfer $end
$var reg 8 % data_in [7:0] $end
$var reg 1 & spi_miso $end
$var wire 1 ' transfer_done $end
$var wire 8 ( data_out [7:0] $end
$var wire 1 ) spi_sck $end
$var wire 1 * spi_mosi $end
$var reg 8 + expected_rx_data [7:0] $end
$var reg 8 , miso_shift_reg [7:0] $end
$var integer 32 - bit_count $end
$var integer 32 . test_count $end
$var integer 32 / error_count $end
$var real 32 0 sck_period $end
$var time 64 1 last_sck_time $end
$var time 64 2 transfer_start_time $end
$var time 64 3 transfer_end_time $end
$var parameter 32 4 CLK_PERIOD [31:0] $end
$var parameter 8 5 TEST_DATA_TX [7:0] $end
$var parameter 8 6 TEST_DATA_RX [7:0] $end
$scope module DUT $end
$var wire 1 7 clk $end
$var wire 1 8 rst_n $end
$var wire 8 9 spi_clk_div [7:0] $end
$var wire 1 : start_transfer $end
$var reg 1 ; transfer_done $end
$var wire 8 < data_in [7:0] $end
$var reg 8 = data_out [7:0] $end
$var reg 1 > spi_sck $end
$var reg 1 ? spi_mosi $end
$var wire 1 @ spi_miso $end
$var reg 2 A current_state [1:0] $end
$var reg 2 B next_state [1:0] $end
$var reg 8 C sck_counter [7:0] $end
$var reg 1 D sck_tick $end
$var reg 4 E bit_counter [3:0] $end
$var reg 8 F shift_reg_tx [7:0] $end
$var reg 8 G shift_reg_rx [7:0] $end
$upscope $end
$scope task test_spi_transfer $end
$var reg 8 H tx_data [7:0] $end
$var reg 8 I rx_data [7:0] $end
$upscope $end
$upscope $end
$enddefinitions $end
#0
$dumpvars
0!
0"
b100 #
0$
b0 %
0&
0'
b0 (
0)
0*
bx +
bx ,
b0 -
b0 .
b0 /
r0 0
b0 1
bx 2
bx 3
b1010 4
b10100101 5
b1011010 6
07
08
b100 9
0:
0;
b0 <
b0 =
0>
0?
0@
b0 A
b0 B
b0 C
0D
b0 E
b0 F
b0 G
bx H
bx I
$end
#5000
1!
17
#10000
0!
07
#15000
1!
17
#20000
0!
07
#25000
1!
17
#30000
0!
07
#35000
1!
17
#40000
0!
07
#45000
1!
1"
17
18
#50000
0!
07
#55000
1!
17
#60000
0!
07
#65000
1!
b10100101 %
b1011010 +
b1011010 ,
b1 .
17
b10100101 <
b10100101 H
b1011010 I
#70000
0!
07
#75000
1!
1$
b1001011 2
17
1:
b1 B
b10100101 F
#80000
0!
07
#85000
1!
0$
17
0:
b1 A
b1 B
#90000
0!
07
#95000
1!
1*
17
1?
b1 C
#100000
0!
07
#105000
1!
17
b10 C
#110000
0!
07
#115000
1!
17
b11 C
#120000
0!
07
#125000
1!
0&
1)
b1 -
b1111101 1
17
1>
b0 C
1D
#130000
0!
07
#135000
1!
17
b1 C
0D
b1 E
b1001010 F
#140000
0!
07
#145000
1!
0*
17
0?
b10 C
#150000
0!
07
#155000
1!
17
b11 C
#160000
0!
07
#165000
1!
0)
17
0>
b0 C
1D
#170000
0!
07
#175000
1!
17
b1 C
0D
#180000
0!
07
#185000
1!
17
b10 C
#190000
0!
07
#195000
1!
17
b11 C
#200000
0!
07
#205000
1!
1&
1)
b10 -
r80 0
b11001101 1
17
1>
1@
b0 C
1D
#210000
0!
07
#215000
1!
17
b1 C
0D
b10 E
b10010100 F
b1 G
#220000
0!
07
#225000
1!
1*
17
1?
b10 C
#230000
0!
07
#235000
1!
17
b11 C
#240000
0!
07
#245000
1!
0)
17
0>
b0 C
1D
#250000
0!
07
#255000
1!
17
b1 C
0D
#260000
0!
07
#265000
1!
17
b10 C
#270000
0!
07
#275000
1!
17
b11 C
#280000
0!
07
#285000
1!
0&
1)
b11 -
b100011101 1
17
1>
0@
b0 C
1D
#290000
0!
07
#295000
1!
17
b1 C
0D
b11 E
b101000 F
b10 G
#300000
0!
07
#305000
1!
0*
17
0?
b10 C
#310000
0!
07
#315000
1!
17
b11 C
#320000
0!
07
#325000
1!
0)
17
0>
b0 C
1D
#330000
0!
07
#335000
1!
17
b1 C
0D
#340000
0!
07
#345000
1!
17
b10 C
#350000
0!
07
#355000
1!
17
b11 C
#360000
0!
07
#365000
1!
1&
1)
b100 -
b101101101 1
17
1>
1@
b0 C
1D
#370000
0!
07
#375000
1!
17
b1 C
0D
b100 E
b1010000 F
b101 G
#380000
0!
07
#385000
1!
17
b10 C
#390000
0!
07
#395000
1!
17
b11 C
#400000
0!
07
#405000
1!
0)
17
0>
b0 C
1D
#410000
0!
07
#415000
1!
17
b1 C
0D
#420000
0!
07
#425000
1!
17
b10 C
#430000
0!
07
#435000
1!
17
b11 C
#440000
0!
07
#445000
1!
1&
1)
b101 -
b110111101 1
17
1>
b0 C
1D
#450000
0!
07
#455000
1!
17
b1 C
0D
b101 E
b10100000 F
b1011 G
#460000
0!
07
#465000
1!
1*
17
1?
b10 C
#470000
0!
07
#475000
1!
17
b11 C
#480000
0!
07
#485000
1!
0)
17
0>
b0 C
1D
#490000
0!
07
#495000
1!
17
b1 C
0D
#500000
0!
07
#505000
1!
17
b10 C
#510000
0!
07
#515000
1!
17
b11 C
#520000
0!
07
#525000
1!
0&
1)
b110 -
b1000001101 1
17
1>
0@
b0 C
1D
#530000
0!
07
#535000
1!
17
b1 C
0D
b110 E
b1000000 F
b10110 G
#540000
0!
07
#545000
1!
0*
17
0?
b10 C
#550000
0!
07
#555000
1!
17
b11 C
#560000
0!
07
#565000
1!
0)
17
0>
b0 C
1D
#570000
0!
07
#575000
1!
17
b1 C
0D
#580000
0!
07
#585000
1!
17
b10 C
#590000
0!
07
#595000
1!
17
b11 C
#600000
0!
07
#605000
1!
1&
1)
b111 -
b1001011101 1
17
1>
1@
b0 C
1D
#610000
0!
07
#615000
1!
17
b1 C
0D
b111 E
b10000000 F
b101101 G
#620000
0!
07
#625000
1!
1*
17
1?
b10 C
#630000
0!
07
#635000
1!
17
b11 C
#640000
0!
07
#645000
1!
0)
17
0>
b0 C
1D
#650000
0!
07
#655000
1!
17
b1 C
0D
#660000
0!
07
#665000
1!
17
b10 C
#670000
0!
07
#675000
1!
17
b11 C
#680000
0!
07
#685000
1!
0&
1)
b1000 -
b1010101101 1
17
1>
0@
b0 C
1D
#690000
0!
07
#695000
1!
17
b10 B
b1 C
0D
b1000 E
b0 F
b1011010 G
#700000
0!
07
#705000
1!
0*
17
0?
b10 A
b0 B
b10 C
#710000
0!
07
#715000
1!
1'
b1011010 (
0)
b1011001011 3
17
1;
b1011010 =
0>
b0 A
b0 C
#720000
0!
07
#725000
1!
0'
17
0;
#730000
0!
07
#735000
1!
17
#740000
0!
07
#745000
1!
17
#750000
0!
07
#755000
1!
17
#760000
0!
07
#765000
1!
b0 %
b11111111 +
b11111111 ,
b0 -
b10 .
17
b0 <
b0 H
b11111111 I
#770000
0!
07
#775000
1!
1$
b1100000111 2
17
1:
b1 B
b0 E
#780000
0!
07
#785000
1!
0$
17
0:
b1 A
b1 B
#790000
0!
07
#795000
1!
17
b1 C
#800000
0!
07
#805000
1!
17
b10 C
#810000
0!
07
#815000
1!
17
b11 C
#820000
0!
07
#825000
1!
1&
1)
b1 -
r140 0
b1100111001 1
17
1>
1@
b0 C
1D
#830000
0!
07
#835000
1!
17
b1 C
0D
b1 E
b10110101 G
#840000
0!
07
#845000
1!
17
b10 C
#850000
0!
07
#855000
1!
17
b11 C
#860000
0!
07
#865000
1!
0)
17
0>
b0 C
1D
#870000
0!
07
#875000
1!
17
b1 C
0D
#880000
0!
07
#885000
1!
17
b10 C
#890000
0!
07
#895000
1!
17
b11 C
#900000
0!
07
#905000
1!
1&
1)
b10 -
r80 0
b1110001001 1
17
1>
b0 C
1D
#910000
0!
07
#915000
1!
17
b1 C
0D
b10 E
b1101011 G
#920000
0!
07
#925000
1!
17
b10 C
#930000
0!
07
#935000
1!
17
b11 C
#940000
0!
07
#945000
1!
0)
17
0>
b0 C
1D
#950000
0!
07
#955000
1!
17
b1 C
0D
#960000
0!
07
#965000
1!
17
b10 C
#970000
0!
07
#975000
1!
17
b11 C
#980000
0!
07
#985000
1!
1&
1)
b11 -
b1111011001 1
17
1>
b0 C
1D
#990000
0!
07
#995000
1!
17
b1 C
0D
b11 E
b11010111 G
#1000000
0!
07
#1005000
1!
17
b10 C
#1010000
0!
07
#1015000
1!
17
b11 C
#1020000
0!
07
#1025000
1!
0)
17
0>
b0 C
1D
#1030000
0!
07
#1035000
1!
17
b1 C
0D
#1040000
0!
07
#1045000
1!
17
b10 C
#1050000
0!
07
#1055000
1!
17
b11 C
#1060000
0!
07
#1065000
1!
1&
1)
b100 -
b10000101001 1
17
1>
b0 C
1D
#1070000
0!
07
#1075000
1!
17
b1 C
0D
b100 E
b10101111 G
#1080000
0!
07
#1085000
1!
17
b10 C
#1090000
0!
07
#1095000
1!
17
b11 C
#1100000
0!
07
#1105000
1!
0)
17
0>
b0 C
1D
#1110000
0!
07
#1115000
1!
17
b1 C
0D
#1120000
0!
07
#1125000
1!
17
b10 C
#1130000
0!
07
#1135000
1!
17
b11 C
#1140000
0!
07
#1145000
1!
1&
1)
b101 -
b10001111001 1
17
1>
b0 C
1D
#1150000
0!
07
#1155000
1!
17
b1 C
0D
b101 E
b1011111 G
#1160000
0!
07
#1165000
1!
17
b10 C
#1170000
0!
07
#1175000
1!
17
b11 C
#1180000
0!
07
#1185000
1!
0)
17
0>
b0 C
1D
#1190000
0!
07
#1195000
1!
17
b1 C
0D
#1200000
0!
07
#1205000
1!
17
b10 C
#1210000
0!
07
#1215000
1!
17
b11 C
#1220000
0!
07
#1225000
1!
1&
1)
b110 -
b10011001001 1
17
1>
b0 C
1D
#1230000
0!
07
#1235000
1!
17
b1 C
0D
b110 E
b10111111 G
#1240000
0!
07
#1245000
1!
17
b10 C
#1250000
0!
07
#1255000
1!
17
b11 C
#1260000
0!
07
#1265000
1!
0)
17
0>
b0 C
1D
#1270000
0!
07
#1275000
1!
17
b1 C
0D
#1280000
0!
07
#1285000
1!
17
b10 C
#1290000
0!
07
#1295000
1!
17
b11 C
#1300000
0!
07
#1305000
1!
1&
1)
b111 -
b10100011001 1
17
1>
b0 C
1D
#1310000
0!
07
#1315000
1!
17
b1 C
0D
b111 E
b1111111 G
#1320000
0!
07
#1325000
1!
17
b10 C
#1330000
0!
07
#1335000
1!
17
b11 C
#1340000
0!
07
#1345000
1!
0)
17
0>
b0 C
1D
#1350000
0!
07
#1355000
1!
17
b1 C
0D
#1360000
0!
07
#1365000
1!
17
b10 C
#1370000
0!
07
#1375000
1!
17
b11 C
#1380000
0!
07
#1385000
1!
1&
1)
b1000 -
b10101101001 1
17
1>
b0 C
1D
#1390000
0!
07
#1395000
1!
17
b10 B
b1 C
0D
b1000 E
b11111111 G
#1400000
0!
07
#1405000
1!
17
b10 A
b0 B
b10 C
#1410000
0!
07
#1415000
1!
1'
b11111111 (
0)
b10110000111 3
17
1;
b11111111 =
0>
b0 A
b0 C
#1420000
0!
07
#1425000
1!
0'
17
0;
#1430000
0!
07
#1435000
1!
17
#1440000
0!
07
#1445000
1!
17
#1450000
0!
07
#1455000
1!
17
#1460000
0!
07
#1465000
1!
b11111111 %
b0 +
b0 ,
b0 -
b11 .
17
b11111111 <
b11111111 H
b0 I
#1470000
0!
07
#1475000
1!
1$
b10111000011 2
17
1:
b1 B
b0 E
b11111111 F
#1480000
0!
07
#1485000
1!
0$
17
0:
b1 A
b1 B
#1490000
0!
07
#1495000
1!
1*
17
1?
b1 C
#1500000
0!
07
#1505000
1!
17
b10 C
#1510000
0!
07
#1515000
1!
17
b11 C
#1520000
0!
07
#1525000
1!
0&
1)
b1 -
r140 0
b10111110101 1
17
1>
0@
b0 C
1D
#1530000
0!
07
#1535000
1!
17
b1 C
0D
b1 E
b11111110 F
b11111110 G
#1540000
0!
07
#1545000
1!
17
b10 C
#1550000
0!
07
#1555000
1!
17
b11 C
#1560000
0!
07
#1565000
1!
0)
17
0>
b0 C
1D
#1570000
0!
07
#1575000
1!
17
b1 C
0D
#1580000
0!
07
#1585000
1!
17
b10 C
#1590000
0!
07
#1595000
1!
17
b11 C
#1600000
0!
07
#1605000
1!
0&
1)
b10 -
r80 0
b11001000101 1
17
1>
b0 C
1D
#1610000
0!
07
#1615000
1!
17
b1 C
0D
b10 E
b11111100 F
b11111100 G
#1620000
0!
07
#1625000
1!
17
b10 C
#1630000
0!
07
#1635000
1!
17
b11 C
#1640000
0!
07
#1645000
1!
0)
17
0>
b0 C
1D
#1650000
0!
07
#1655000
1!
17
b1 C
0D
#1660000
0!
07
#1665000
1!
17
b10 C
#1670000
0!
07
#1675000
1!
17
b11 C
#1680000
0!
07
#1685000
1!
0&
1)
b11 -
b11010010101 1
17
1>
b0 C
1D
#1690000
0!
07
#1695000
1!
17
b1 C
0D
b11 E
b11111000 F
b11111000 G
#1700000
0!
07
#1705000
1!
17
b10 C
#1710000
0!
07
#1715000
1!
17
b11 C
#1720000
0!
07
#1725000
1!
0)
17
0>
b0 C
1D
#1730000
0!
07
#1735000
1!
17
b1 C
0D
#1740000
0!
07
#1745000
1!
17
b10 C
#1750000
0!
07
#1755000
1!
17
b11 C
#1760000
0!
07
#1765000
1!
0&
1)
b100 -
b11011100101 1
17
1>
b0 C
1D
#1770000
0!
07
#1775000
1!
17
b1 C
0D
b100 E
b11110000 F
b11110000 G
#1780000
0!
07
#1785000
1!
17
b10 C
#1790000
0!
07
#1795000
1!
17
b11 C
#1800000
0!
07
#1805000
1!
0)
17
0>
b0 C
1D
#1810000
0!
07
#1815000
1!
17
b1 C
0D
#1820000
0!
07
#1825000
1!
17
b10 C
#1830000
0!
07
#1835000
1!
17
b11 C
#1840000
0!
07
#1845000
1!
0&
1)
b101 -
b11100110101 1
17
1>
b0 C
1D
#1850000
0!
07
#1855000
1!
17
b1 C
0D
b101 E
b11100000 F
b11100000 G
#1860000
0!
07
#1865000
1!
17
b10 C
#1870000
0!
07
#1875000
1!
17
b11 C
#1880000
0!
07
#1885000
1!
0)
17
0>
b0 C
1D
#1890000
0!
07
#1895000
1!
17
b1 C
0D
#1900000
0!
07
#1905000
1!
17
b10 C
#1910000
0!
07
#1915000
1!
17
b11 C
#1920000
0!
07
#1925000
1!
0&
1)
b110 -
b11110000101 1
17
1>
b0 C
1D
#1930000
0!
07
#1935000
1!
17
b1 C
0D
b110 E
b11000000 F
b11000000 G
#1940000
0!
07
#1945000
1!
17
b10 C
#1950000
0!
07
#1955000
1!
17
b11 C
#1960000
0!
07
#1965000
1!
0)
17
0>
b0 C
1D
#1970000
0!
07
#1975000
1!
17
b1 C
0D
#1980000
0!
07
#1985000
1!
17
b10 C
#1990000
0!
07
#1995000
1!
17
b11 C
#2000000
0!
07
#2005000
1!
0&
1)
b111 -
b11111010101 1
17
1>
b0 C
1D
#2010000
0!
07
#2015000
1!
17
b1 C
0D
b111 E
b10000000 F
b10000000 G
#2020000
0!
07
#2025000
1!
17
b10 C
#2030000
0!
07
#2035000
1!
17
b11 C
#2040000
0!
07
#2045000
1!
0)
17
0>
b0 C
1D
#2050000
0!
07
#2055000
1!
17
b1 C
0D
#2060000
0!
07
#2065000
1!
17
b10 C
#2070000
0!
07
#2075000
1!
17
b11 C
#2080000
0!
07
#2085000
1!
0&
1)
b1000 -
b100000100101 1
17
1>
b0 C
1D
#2090000
0!
07
#2095000
1!
17
b10 B
b1 C
0D
b1000 E
b0 F
b0 G
#2100000
0!
07
#2105000
1!
0*
17
0?
b10 A
b0 B
b10 C
#2110000
0!
07
#2115000
1!
1'
b0 (
0)
b100001000011 3
17
1;
b0 =
0>
b0 A
b0 C
#2120000
0!
07
#2125000
1!
0'
17
0;
#2130000
0!
07
#2135000
1!
17
#2140000
0!
07
#2145000
1!
17
#2150000
0!
07
#2155000
1!
17
#2160000
0!
07
#2165000
1!
b10101010 %
b1010101 +
b1010101 ,
b0 -
b100 .
17
b10101010 <
b10101010 H
b1010101 I
#2170000
0!
07
#2175000
1!
1$
b100001111111 2
17
1:
b1 B
b0 E
b10101010 F
#2180000
0!
07
#2185000
1!
0$
17
0:
b1 A
b1 B
#2190000
0!
07
#2195000
1!
1*
17
1?
b1 C
#2200000
0!
07
#2205000
1!
17
b10 C
#2210000
0!
07
#2215000
1!
17
b11 C
#2220000
0!
07
#2225000
1!
0&
1)
b1 -
r140 0
b100010110001 1
17
1>
b0 C
1D
#2230000
0!
07
#2235000
1!
17
b1 C
0D
b1 E
b1010100 F
#2240000
0!
07
#2245000
1!
0*
17
0?
b10 C
#2250000
0!
07
#2255000
1!
17
b11 C
#2260000
0!
07
#2265000
1!
0)
17
0>
b0 C
1D
#2270000
0!
07
#2275000
1!
17
b1 C
0D
#2280000
0!
07
#2285000
1!
17
b10 C
#2290000
0!
07
#2295000
1!
17
b11 C
#2300000
0!
07
#2305000
1!
1&
1)
b10 -
r80 0
b100100000001 1
17
1>
1@
b0 C
1D
#2310000
0!
07
#2315000
1!
17
b1 C
0D
b10 E
b10101000 F
b1 G
#2320000
0!
07
#2325000
1!
1*
17
1?
b10 C
#2330000
0!
07
#2335000
1!
17
b11 C
#2340000
0!
07
#2345000
1!
0)
17
0>
b0 C
1D
#2350000
0!
07
#2355000
1!
17
b1 C
0D
#2360000
0!
07
#2365000
1!
17
b10 C
#2370000
0!
07
#2375000
1!
17
b11 C
#2380000
0!
07
#2385000
1!
0&
1)
b11 -
b100101010001 1
17
1>
0@
b0 C
1D
#2390000
0!
07
#2395000
1!
17
b1 C
0D
b11 E
b1010000 F
b10 G
#2400000
0!
07
#2405000
1!
0*
17
0?
b10 C
#2410000
0!
07
#2415000
1!
17
b11 C
#2420000
0!
07
#2425000
1!
0)
17
0>
b0 C
1D
#2430000
0!
07
#2435000
1!
17
b1 C
0D
#2440000
0!
07
#2445000
1!
17
b10 C
#2450000
0!
07
#2455000
1!
17
b11 C
#2460000
0!
07
#2465000
1!
1&
1)
b100 -
b100110100001 1
17
1>
1@
b0 C
1D
#2470000
0!
07
#2475000
1!
17
b1 C
0D
b100 E
b10100000 F
b101 G
#2480000
0!
07
#2485000
1!
1*
17
1?
b10 C
#2490000
0!
07
#2495000
1!
17
b11 C
#2500000
0!
07
#2505000
1!
0)
17
0>
b0 C
1D
#2510000
0!
07
#2515000
1!
17
b1 C
0D
#2520000
0!
07
#2525000
1!
17
b10 C
#2530000
0!
07
#2535000
1!
17
b11 C
#2540000
0!
07
#2545000
1!
0&
1)
b101 -
b100111110001 1
17
1>
0@
b0 C
1D
#2550000
0!
07
#2555000
1!
17
b1 C
0D
b101 E
b1000000 F
b1010 G
#2560000
0!
07
#2565000
1!
0*
17
0?
b10 C
#2570000
0!
07
#2575000
1!
17
b11 C
#2580000
0!
07
#2585000
1!
0)
17
0>
b0 C
1D
#2590000
0!
07
#2595000
1!
17
b1 C
0D
#2600000
0!
07
#2605000
1!
17
b10 C
#2610000
0!
07
#2615000
1!
17
b11 C
#2620000
0!
07
#2625000
1!
1&
1)
b110 -
b101001000001 1
17
1>
1@
b0 C
1D
#2630000
0!
07
#2635000
1!
17
b1 C
0D
b110 E
b10000000 F
b10101 G
#2640000
0!
07
#2645000
1!
1*
17
1?
b10 C
#2650000
0!
07
#2655000
1!
17
b11 C
#2660000
0!
07
#2665000
1!
0)
17
0>
b0 C
1D
#2670000
0!
07
#2675000
1!
17
b1 C
0D
#2680000
0!
07
#2685000
1!
17
b10 C
#2690000
0!
07
#2695000
1!
17
b11 C
#2700000
0!
07
#2705000
1!
0&
1)
b111 -
b101010010001 1
17
1>
0@
b0 C
1D
#2710000
0!
07
#2715000
1!
17
b1 C
0D
b111 E
b0 F
b101010 G
#2720000
0!
07
#2725000
1!
0*
17
0?
b10 C
#2730000
0!
07
#2735000
1!
17
b11 C
#2740000
0!
07
#2745000
1!
0)
17
0>
b0 C
1D
#2750000
0!
07
#2755000
1!
17
b1 C
0D
#2760000
0!
07
#2765000
1!
17
b10 C
#2770000
0!
07
#2775000
1!
17
b11 C
#2780000
0!
07
#2785000
1!
1&
1)
b1000 -
b101011100001 1
17
1>
1@
b0 C
1D
#2790000
0!
07
#2795000
1!
17
b10 B
b1 C
0D
b1000 E
b1010101 G
#2800000
0!
07
#2805000
1!
17
b10 A
b0 B
b10 C
#2810000
0!
07
#2815000
1!
1'
b1010101 (
0)
b101011111111 3
17
1;
b1010101 =
0>
b0 A
b0 C
#2820000
0!
07
#2825000
1!
0'
17
0;
#2830000
0!
07
#2835000
1!
17
#2840000
0!
07
#2845000
1!
17
#2850000
0!
07
#2855000
1!
17
#2860000
0!
07
#2865000
1!
b1000 #
b111100 %
b11000011 +
b11000011 ,
b0 -
b101 .
17
b1000 9
b111100 <
b111100 H
b11000011 I
#2870000
0!
07
#2875000
1!
1$
b101100111011 2
17
1:
b1 B
b0 E
b111100 F
#2880000
0!
07
#2885000
1!
0$
17
0:
b1 A
b1 B
#2890000
0!
07
#2895000
1!
17
b1 C
#2900000
0!
07
#2905000
1!
17
b10 C
#2910000
0!
07
#2915000
1!
17
b11 C
#2920000
0!
07
#2925000
1!
17
b100 C
#2930000
0!
07
#2935000
1!
17
b101 C
#2940000
0!
07
#2945000
1!
17
b110 C
#2950000
0!
07
